Workbook

Sheet Lab Diamond Jewelry
A1: LAB DIAMOND JEWELRY — 18K GOLD & 925 STERLING SILVER
A2: Cheapest option kept per design · Listed prices are the sites’ RETAIL prices · Set your wholesale discount, costs and profit % on the Pricing sheet — every figure below recalculates
A3: # | B3: Photo | C3: Product Name | D3: Category | E3: Description | F3: Metal | G3: Stone | H3: Weight (ct) | I3: Weight / Size (as stated) | J3: Stone Spec | K3: Listed Price (USD) retail on the site | L3: Your Cost (USD) after wholesale discount | M3: Landed Cost (SAR) incl. shipping, customs, fees | N3: FINAL PRICE (SAR) | O3: Profit (SAR) | P3: Product Link | Q3: Source | R3: Image URL | S3: Variants Merged
A4: 1 | C4: Round Lab Diamond Pave Force Rope Chain Bracelet | D4: Bracelet | E4: Stone Spec: Round Cut Lab Diamond DEF VS, 0.78 ct tw Please note, kindly specify your bracelet size in the remarks when placing the order. If you have any special requests for this design (such as metal, gemstone, or design details), please contact our advisor for customization. Description Bold and contemporary, this force rope chain bracelet features shimmering round lab diamonds in a refined pavé setting , combining the strength of classic chain styling with elevated fine jewelry brilliance. The intertwined rope-inspired links create rich texture and dimension, giving the piece a powerful… | F4: 925 Sterling Silver | G4: Lab Grown Diamond | H4: 0.78 | I4: 0.78 ct | J4: 0.78 ct tw round cut DEF VVS-VS | K4: 1063.2 | L4: =K4*(1-Pricing!$B$4) | M4: =L4*Pricing!$B$9*(1+Pricing!$B$6+Pricing!$B$7)+Pricing!$B$5 | N4: =M4*(1+Pricing!$B$8) | O4: =N4-M4 | P4: View Product | Q4: Fiorese Jewelry | R4: Open Image | S4: 1
A5: 2 | C5: Round Lab Diamond Heart Pendant Charm Bracelet | D5: Bracelet | E5: Stone Spec: Round Cut Lab Diamond DEF VS Please note, kindly specify your bracelet size in the remarks when placing the order. If you have any special requests for this design (such as metal, gemstone, or design details), please contact our advisor for customization. Description Sweet and refined, this charm bracelet features a delicate chain accented with a heart-shaped pendant adorned with round lab diamonds , symbolizing love with a soft, radiant sparkle. The round diamonds add timeless brilliance, while the heart motif brings a romantic and meaningful touch. The lightweight chain… | F5: 18K Gold | G5: Lab Grown Diamond | I5: 2mm (per stone) | J5: 4 pieces 2mm + 13 pieces 1mm DEF VS | K5: 1204 | L5: =K5*(1-Pricing!$B$4) | M5: =L5*Pricing!$B$9*(1+Pricing!$B$6+Pricing!$B$7)+Pricing!$B$5 | N5: =M5*(1+Pricing!$B$8) | O5: =N5-M5 | P5: View Product | Q5: Fiorese Jewelry | R5: Open Image | S5: 1
A6: 3 | C6: 3.5mm Round Lab Diamond 3-Stone Bezel-Set Adjustable Station Bracelet | D6: Bracelet | E6: Stone Spec: 3.5mm Round Cut Lab Diamond, DEF VS, about 0.45 ct tw Please note, kindly specify your bracelet size in the remarks when placing the order. If you have any special requests for this design (such as metal, gemstone, or design details), please contact our advisor for customization. Description Delicate and effortlessly refined, this adjustable station bracelet features three 3.5mm round lab diamonds , thoughtfully spaced along a fine chain to create a balanced and airy silhouette. The trio of stones symbolizes harmony and continuity, adding subtle meaning to its elegant design.… | F6: 18K Gold | G6: Lab Grown Diamond | H6: 0.45 | I6: 0.45 ct | J6: 3 pieces of 3.5mm round cut | K6: 1300.8 | L6: =K6*(1-Pricing!$B$4) | M6: =L6*Pricing!$B$9*(1+Pricing!$B$6+Pricing!$B$7)+Pricing!$B$5 | N6: =M6*(1+Pricing!$B$8) | O6: =N6-M6 | P6: View Product | Q6: Fiorese Jewelry | R6: Open Image | S6: 1
A7: 4 | C7: Round Lab Diamond Toi et Moi Pendant Chain Bracelet | D7: Bracelet | E7: Stone Spec: 1.2mm Radiant Cut Lab Diamond DEF VS, about 0.17 ct tw Pendant Size: 25*6.6mm Please note, kindly specify your bracelet size in the remarks when placing the order. If you have any special requests for this design (such as metal, gemstone, or design details), please contact our advisor for customization. Description Refined and meaningful, this chain bracelet features a distinctive Toi-et-Moi pendant , pairing a round lab diamond centerpiece with a rectangular ring motif set with pavé lab diamonds . The interplay of shapes symbolizes two elements in harmony—soft brilliance meeting… | F7: 18K Gold | G7: Lab Grown Diamond | H7: 0.17 | I7: 0.17 ct | J7: 22 pieces of 1.2mm round cut DEF VS | K7: 1423.2 | L7: =K7*(1-Pricing!$B$4) | M7: =L7*Pricing!$B$9*(1+Pricing!$B$6+Pricing!$B$7)+Pricing!$B$5 | N7: =M7*(1+Pricing!$B$8) | O7: =N7-M7 | P7: View Product | Q7: Fiorese Jewelry | R7: Open Image | S7: 1
A8: 5 | C8: 3mm Round Lab Diamond Bezel-Set Station Bracelet | D8: Bracelet | E8: Stone Spec: 3mm Round Cut Lab Diamond, DEF VS, about 0.77 ct tw Please note, kindly specify your bracelet size in the remarks when placing the order. If you have any special requests for this design (such as metal, gemstone, or design details), please contact our advisor for customization. Description Clean and effortlessly refined, this station bracelet features 3mm round lab diamonds delicately spaced along a fine chain, creating a light, balanced silhouette with subtle, continuous sparkle. The station design offers an airy, modern feel that complements both everyday wear and layered… | F8: 18K Gold | G8: Lab Grown Diamond | H8: 0.77 | I8: 0.77 ct | J8: 7 pieces of 3mm DEF VS | K8: 1423.2 | L8: =K8*(1-Pricing!$B$4) | M8: =L8*Pricing!$B$9*(1+Pricing!$B$6+Pricing!$B$7)+Pricing!$B$5 | N8: =M8*(1+Pricing!$B$8) | O8: =N8-M8 | P8: View Product | Q8: Fiorese Jewelry | R8: Open Image | S8: 1
A9: 6 | C9: 3mm Round Lab Diamond 5-Stone Bezel-Set Adjustable Station Bracelet | D9: Bracelet | E9: Stone Spec: 3mm Round Cut Lab Diamond, DEF VS, about 0.5 ct tw Please note, kindly specify your bracelet size in the remarks when placing the order. If you have any special requests for this design (such as metal, gemstone, or design details), please contact our advisor for customization. Description Light, refined, and effortlessly wearable, this adjustable station bracelet features five 3mm round lab diamonds , evenly spaced along a fine chain to create a graceful, balanced silhouette. The five-stone arrangement adds a subtle rhythm of sparkle while maintaining a clean, minimalist… | F9: 18K Gold | G9: Lab Grown Diamond | H9: 0.5 | I9: 0.5 ct | J9: 5 pieces of 3mm round cut | K9: 1473.6 | L9: =K9*(1-Pricing!$B$4) | M9: =L9*Pricing!$B$9*(1+Pricing!$B$6+Pricing!$B$7)+Pricing!$B$5 | N9: =M9*(1+Pricing!$B$8) | O9: =N9-M9 | P9: View Product | Q9: Fiorese Jewelry | R9: Open Image | S9: 1
A10: 7 | C10: Round Lab Diamond Leaf-Cluster Chain Bracelet | D10: Bracelet | E10: Stone Spec: Round Cut Lab Diamond DEF VS, about 0.3 ct tw Cluster Length: 32mm Please note, kindly specify your bracelet size in the remarks when placing the order. If you have any special requests for this design (such as metal, gemstone, or design details), please contact our advisor for customization. Description Graceful and organically inspired, this chain bracelet features clusters of round lab diamonds arranged in a delicate leaf motif , creating a soft, flowing pattern along the wrist. Each cluster evokes the natural beauty of foliage, blending structure with gentle movement. The… | F10: 18K Gold | G10: Lab Grown Diamond | H10: 0.3 | I10: 0.3 ct | J10: Round Cut DEF VS | K10: 1703.2 | L10: =K10*(1-Pricing!$B$4) | M10: =L10*Pricing!$B$9*(1+Pricing!$B$6+Pricing!$B$7)+Pricing!$B$5 | N10: =M10*(1+Pricing!$B$8) | O10: =N10-M10 | P10: View Product | Q10: Fiorese Jewelry | R10: Open Image | S10: 1
A11: 8 | C11: Round Lab Diamond Viper-Inspired Bangle Bracelet | D11: Bracelet | E11: Stone Spec: Round Cut Lab Diamond DEF VS about 3.66 ct tw Please note, kindly specify your bracelet size in the remarks when placing the order. If you have any special requests for this design (such as metal, gemstone, or design details), please contact our advisor for customization. Description Bold, sculptural, and undeniably captivating, this viper-inspired bangle bracelet features shimmering round lab diamonds arranged within a sleek serpentine silhouette that wraps gracefully around the wrist. Inspired by the fluid movement and striking elegance of a serpent, the design embodies both… | F11: 925 Sterling Silver | G11: Lab Grown Diamond | H11: 3.66 | I11: 3.66 ct | J11: Round Lab Diamond DEF VVS-VS | K11: 1809.6 | L11: =K11*(1-Pricing!$B$4) | M11: =L11*Pricing!$B$9*(1+Pricing!$B$6+Pricing!$B$7)+Pricing!$B$5 | N11: =M11*(1+Pricing!$B$8) | O11: =N11-M11 | P11: View Product | Q11: Fiorese Jewelry | R11: Open Image | S11: 1
A12: 9 | C12: Round Lab Diamond Star Bezel-Set Station Bracelet | D12: Bracelet | E12: Stone Spec: Round Cut Lab Diamond DEF VS Stone Size Guide (Based on 6" Bracelet) Total Carat Weight ~1.62 ct tw Please note, kindly specify your bracelet size in the remarks when placing the order. If you have any special requests for this design (such as metal, gemstone, or design details), please contact our advisor for customization. Description Whimsical and refined, this station bracelet features round lab diamonds framed in distinctive star-shaped bezel settings , creating a celestial-inspired design that feels both playful and sophisticated. Each star gently highlights the diamond at… | F12: 18K Gold | G12: Lab Grown Diamond | H12: 1.62 | I12: 1.62 ct | J12: 1.8mm round cut lab diamond DEF VVS-VS | K12: 2132.8 | L12: =K12*(1-Pricing!$B$4) | M12: =L12*Pricing!$B$9*(1+Pricing!$B$6+Pricing!$B$7)+Pricing!$B$5 | N12: =M12*(1+Pricing!$B$8) | O12: =N12-M12 | P12: View Product | Q12: Fiorese Jewelry | R12: Open Image | S12: 2
A13: 10 | C13: Round Lab Diamond Ring-Shaped Pave Pendant Chain Bracelet | D13: Bracelet | E13: Stone Spec: 1.5mm Round Cut Lab Diamond DEF VS, about 0.57 ct tw Pendant Size: 23mm Please note, kindly specify your bracelet size in the remarks when placing the order. If you have any special requests for this design (such as metal, gemstone, or design details), please contact our advisor for customization. Description Modern and symbolic, this chain bracelet features a refined ring-shaped pendant set with round lab diamonds , creating a continuous circle of light that represents unity and eternity. The clean, circular silhouette adds a contemporary elegance with meaningful depth. The… | F13: 18K Gold | G13: Lab Grown Diamond | H13: 0.57 | I13: 0.57 ct | J13: 38 pieces of 1.5mm round cut DEF VVS-VS | K13: 2873.6 | L13: =K13*(1-Pricing!$B$4) | M13: =L13*Pricing!$B$9*(1+Pricing!$B$6+Pricing!$B$7)+Pricing!$B$5 | N13: =M13*(1+Pricing!$B$8) | O13: =N13-M13 | P13: View Product | Q13: Fiorese Jewelry | R13: Open Image | S13: 1
A14: 11 | C14: Round Lab Diamond Fancy-Shape Station Chain Bracelet | D14: Bracelet | E14: Stone Spec: Round Cut Lab Diamond, DEF VS, about 2 ct tw Please note, kindly specify your bracelet size in the remarks when placing the order. If you have any special requests for this design (such as metal, gemstone, or design details), please contact our advisor for customization. Description Playful yet refined, this station chain bracelet features a harmonious mix of round lab diamonds and fancy-shaped accents , creating a dynamic interplay of light and form along a delicate chain. The varied silhouettes add visual interest while maintaining a balanced, elegant composition. Each diamond… | F14: 18K Gold | G14: Lab Grown Diamond | H14: 2 | I14: 2 ct | J14: Round Cut DEF VS about 2 ct tw | K14: 2926.4 | L14: =K14*(1-Pricing!$B$4) | M14: =L14*Pricing!$B$9*(1+Pricing!$B$6+Pricing!$B$7)+Pricing!$B$5 | N14: =M14*(1+Pricing!$B$8) | O14: =N14-M14 | P14: View Product | Q14: Fiorese Jewelry | R14: Open Image | S14: 1
A15: 12 | C15: Round Lab Diamond Pave Force Rope Chain Bracelet | D15: Bracelet | E15: Stone Spec: Round Cut Lab Diamond DEF VS, 0.78 ct tw Please note, kindly specify your bracelet size in the remarks when placing the order. If you have any special requests for this design (such as metal, gemstone, or design details), please contact our advisor for customization. Description Bold and contemporary, this force rope chain bracelet features shimmering round lab diamonds in a refined pavé setting , combining the strength of classic chain styling with elevated fine jewelry brilliance. The intertwined rope-inspired links create rich texture and dimension, giving the piece a powerful… | F15: 18K Gold | G15: Lab Grown Diamond | H15: 0.78 | I15: 0.78 ct | J15: 0.78 ct tw round cut DEF VVS-VS | K15: 3378.4 | L15: =K15*(1-Pricing!$B$4) | M15: =L15*Pricing!$B$9*(1+Pricing!$B$6+Pricing!$B$7)+Pricing!$B$5 | N15: =M15*(1+Pricing!$B$8) | O15: =N15-M15 | P15: View Product | Q15: Fiorese Jewelry | R15: Open Image | S15: 1
A16: 13 | C16: Men's Iced-Out Cuban Link Bracelet with Round Lab Diamonds | D16: Bracelet | E16: Stone Spec: Round Cut Lab Diamond DEF VS Stone Size Guide (Based on 7.8" Bracelet) Total Carat Weight ~9.2 ct tw Please note, kindly specify your bracelet size in the remarks when placing the order. If you have any special requests for this design (such as metal, gemstone, or design details), please contact our advisor for customization. Description Bold, powerful, and unapologetically luxurious, this men’s Cuban link bracelet is fully adorned with round lab diamonds in an iced-out pavé design, creating an intense display of brilliance from every angle. The iconic Cuban link silhouette… | F16: 925 Sterling Silver | G16: Lab Grown Diamond | H16: 9.2 | I16: 9.2 ct | J16: Round Lab Diamond DEF VS | K16: 3603.2 | L16: =K16*(1-Pricing!$B$4) | M16: =L16*Pricing!$B$9*(1+Pricing!$B$6+Pricing!$B$7)+Pricing!$B$5 | N16: =M16*(1+Pricing!$B$8) | O16: =N16-M16 | P16: View Product | Q16: Fiorese Jewelry | R16: Open Image | S16: 1
A17: 14 | C17: Round Lab Diamond Prong Basket Cluster Bracelet | D17: Bracelet | E17: Stone Spec: Round Cut Lab Diamond DEF VS Adjustable Chain Length: 2 inches Stone Size Guide (Based on 7" Bracelet) Total Carat Weight ~4.96 ct tw Please note, kindly specify your bracelet size in the remarks when placing the order. If you have any special requests for this design (such as metal, gemstone, or design details), please contact our advisor for customization. Description Radiant and full of dimension, this cluster bracelet features groups of round lab diamonds arranged in elegant clusters, creating the illusion of larger stones with amplified brilliance. Each cluster is secured in… | F17: 18K Gold | G17: Lab Grown Diamond | H17: 4.96 | I17: 4.96 ct | J17: Round cut lab diamond DEF VS | K17: 4388 | L17: =K17*(1-Pricing!$B$4) | M17: =L17*Pricing!$B$9*(1+Pricing!$B$6+Pricing!$B$7)+Pricing!$B$5 | N17: =M17*(1+Pricing!$B$8) | O17: =N17-M17 | P17: View Product | Q17: Fiorese Jewelry | R17: Open Image | S17: 1
... A19: 16 | C19: Round Cut Lab Diamond 14-Stone Open Bangle Bracelet | D19: Bracelet | E19: Stone Spec: 3.5mm Round Cut Lab Diamond DEF VS, about 2.24 ct tw Width: 2.4mm Thickness: 1.8mm Please note, kindly specify your bracelet size in the remarks when placing the order. If you have any special requests for this design (such as metal, gemstone, or design details), please contact our advisor for customization. Description Elegant and strikingly modern, this open bangle bracelet features 14 round cut lab diamonds arranged along the curved silhouette for a balanced display of brilliance and sophistication. The open design creates a refined contemporary look while allowing the… | F19: 18K Gold | G19: Lab Grown Diamond | H19: 2.24 | I19: 2.24 ct | J19: 14 pieces of round cut lab diamond DEF VVS-VS about 2.24 ct | K19: 5404.8 | L19: =K19*(1-Pricing!$B$4) | M19: =L19*Pricing!$B$9*(1+Pricing!$B$6+Pricing!$B$7)+Pricing!$B$5 | N19: =M19*(1+Pricing!$B$8) | O19: =N19-M19 | P19: View Product | Q19: Fiorese Jewelry | R19: Open Image | S19: 1
A20: 17 | C20: 2.5mm Gemstone Four-Leaf Clover Station Bracelet with Millegrain Bezel | D20: Bracelet | E20: Stone Spec: Round Cut Lab Diamond, DEF VS, and Round Gemstone Please note, kindly specify your bracelet size in the remarks when placing the order. If you have any special requests for this design (such as metal, gemstone, or design details), please contact our advisor for customization. Description Inspired by the timeless symbolism of luck and happiness, this 18K yellow gold station bracelet features a series of delicate four-leaf clover motifs, each formed by four 2.5mm round-cut gemstones. The thoughtfully spaced station design creates a light, graceful silhouette that rests beautifully… | F20: 18K Gold | G20: Lab Grown Diamond | I20: 2.5mm (per stone) | J20: Round Cut Lab Diamond DEF VS and Round Gemstone | K20: 5715.2 | L20: =K20*(1-Pricing!$B$4) | M20: =L20*Pricing!$B$9*(1+Pricing!$B$6+Pricing!$B$7)+Pricing!$B$5 | N20: =M20*(1+Pricing!$B$8) | O20: =N20-M20 | P20: View Product | Q20: Fiorese Jewelry | R20: Open Image | S20: 1
A21: 18 | C21: Oval Cut Lab Diamond Bezel-Set Bangle Bracelet | D21: Bracelet | E21: Stone Spec: Oval Cut Lab Diamond DEF VS, about 2.16 ct tw Please note, kindly specify your bracelet size in the remarks when placing the order. If you have any special requests for this design (such as metal, gemstone, or design details), please contact our advisor for customization. Description Elegant and contemporary, this bangle bracelet features a refined arrangement of oval cut lab diamonds , celebrated for their elongated silhouette and soft, brilliant sparkle. The graceful proportions of the oval cuts create a flattering, fluid line across the wrist with timeless sophistication. Each… | F21: 18K Gold | G21: Lab Grown Diamond | H21: 2.16 | I21: 2.16 ct | J21: 12 pieces of 3*5mm oval cut DEF VS | K21: 8018.4 | L21: =K21*(1-Pricing!$B$4) | M21: =L21*Pricing!$B$9*(1+Pricing!$B$6+Pricing!$B$7)+Pricing!$B$5 | N21: =M21*(1+Pricing!$B$8) | O21: =N21-M21 | P21: View Product | Q21: Fiorese Jewelry | R21: Open Image | S21: 1
A22: 19 | C22: Round Lab Diamond Viper-Inspired Bangle Bracelet | D22: Bracelet | E22: Stone Spec: Round Cut Lab Diamond DEF VS about 3.66 ct tw Please note, kindly specify your bracelet size in the remarks when placing the order. If you have any special requests for this design (such as metal, gemstone, or design details), please contact our advisor for customization. Description Bold, sculptural, and undeniably captivating, this viper-inspired bangle bracelet features shimmering round lab diamonds arranged within a sleek serpentine silhouette that wraps gracefully around the wrist. Inspired by the fluid movement and striking elegance of a serpent, the design embodies both… | F22: 18K Gold | G22: Lab Grown Diamond | H22: 3.66 | I22: 3.66 ct | J22: Round Lab Diamond DEF VVS-VS | K22: 10534.4 | L22: =K22*(1-Pricing!$B$4) | M22: =L22*Pricing!$B$9*(1+Pricing!$B$6+Pricing!$B$7)+Pricing!$B$5 | N22: =M22*(1+Pricing!$B$8) | O22: =N22-M22 | P22: View Product | Q22: Fiorese Jewelry | R22: Open Image | S22: 1
A23: 20 | C23: 24 CT TW Cushion Cut Lab Diamond 4-Claw Prong Basket Station Bracelet | D23: Bracelet | E23: Stone Spec: 6.5mm Cushion Cut Lab Diamond DEF VS Stone Size Guide (Based on 7" Bracelet) Total Carat Weight ~24 ct tw Please note, kindly specify your bracelet size in the remarks when placing the order. If you have any special requests for this design (such as metal, gemstone, or design details), please contact our advisor for customization. Description Bold, luminous, and unapologetically luxurious, this station bracelet features an impressive total of 24 ct tw cushion cut lab diamonds , each chosen for its soft square silhouette and rich, brilliant sparkle. The cushion cut’s rounded… | F23: 18K Gold | G23: Lab Grown Diamond | H23: 24 | I23: 24 ct | J23: 24 pieces of 6.5*6.5mm cushion cut lab diamond DEF VS about | K23: 10956.8 | L23: =K23*(1-Pricing!$B$4) | M23: =L23*Pricing!$B$9*(1+Pricing!$B$6+Pricing!$B$7)+Pricing!$B$5 | N23: =M23*(1+Pricing!$B$8) | O23: =N23-M23 | P23: View Product | Q23: Fiorese Jewelry | R23: Open Image | S23: 1
A24: 21 | C24: Round and Princess Cut Lab Diamond Bezel-Set Bangle Bracelet | D24: Bracelet | E24: Stone Spec: Princess Cut and Round Lab Diamond DEF VS, about 0.87 ct tw Please note, kindly specify your bracelet size in the remarks when placing the order. If you have any special requests for this design (such as metal, gemstone, or design details), please contact our advisor for customization. Description Modern and elegantly structured, this bangle bracelet features a refined combination of round and princess cut lab diamonds , creating a sophisticated contrast between soft brilliance and crisp geometric sparkle. The mixed-shape arrangement adds visual rhythm and contemporary character… | F24: 18K Gold | G24: Lab Grown Diamond | H24: 0.87 | I24: 0.87 ct | J24: Princess Cut and Round Lab Diamond DEF VS / about 0.87 ct tw | K24: 11013.6 | L24: =K24*(1-Pricing!$B$4) | M24: =L24*Pricing!$B$9*(1+Pricing!$B$6+Pricing!$B$7)+Pricing!$B$5 | N24: =M24*(1+Pricing!$B$8) | O24: =N24-M24 | P24: View Product | Q24: Fiorese Jewelry | R24: Open Image | S24: 1
A25: 22 | C25: Knight's Faith Pavé Lab Diamond Bracelet | D25: Bracelet | E25: Stone Spec: Round Cut Lab Diamond DEF VS Stone Size Guide (Based on 7" Bracelet) Total Carat Weight ~6.2 ct tw Please note, kindly specify your bracelet size in the remarks when placing the order. If you have any special requests for this design (such as metal, gemstone, or design details), please contact our advisor for customization. Description Bold, commanding, and richly detailed, the Knight’s Faith Pavé Lab Diamond Bracelet is designed to embody strength, confidence, and refined modern luxury. Adorned with shimmering pavé-set lab diamonds , the bracelet delivers continuous brilliance… | F25: 18K Gold | G25: Lab Grown Diamond | H25: 6.2 | I25: 6.2 ct | J25: Round cut DEF VS | K25: 20387.2 | L25: =K25*(1-Pricing!$B$4) | M25: =L25*Pricing!$B$9*(1+Pricing!$B$6+Pricing!$B$7)+Pricing!$B$5 | N25: =M25*(1+Pricing!$B$8) | O25: =N25-M25 | P25: View Product | Q25: Fiorese Jewelry | R25: Open Image | S25: 1
A26: 23 | C26: Men's Iced-Out Cuban Link Bracelet with Round Lab Diamonds | D26: Bracelet | E26: Stone Spec: Round Cut Lab Diamond DEF VS Stone Size Guide (Based on 7.8" Bracelet) Total Carat Weight ~9.2 ct tw Please note, kindly specify your bracelet size in the remarks when placing the order. If you have any special requests for this design (such as metal, gemstone, or design details), please contact our advisor for customization. Description Bold, powerful, and unapologetically luxurious, this men’s Cuban link bracelet is fully adorned with round lab diamonds in an iced-out pavé design, creating an intense display of brilliance from every angle. The iconic Cuban link silhouette… | F26: 18K Gold | G26: Lab Grown Diamond | H26: 9.2 | I26: 9.2 ct | J26: Round Lab Diamond DEF VS | K26: 39595.2 | L26: =K26*(1-Pricing!$B$4) | M26: =L26*Pricing!$B$9*(1+Pricing!$B$6+Pricing!$B$7)+Pricing!$B$5 | N26: =M26*(1+Pricing!$B$8) | O26: =N26-M26 | P26: View Product | Q26: Fiorese Jewelry | R26: Open Image | S26: 1
A27: 24 | C27: Colored Lab Gemstone Bracelet with 10×14mm Oval Lab Orange Sapphire | D27: Bracelet | E27: Stone Spec: 14*10mm Oval Lab Orange Sapphire and R ound Lab Colored Sapphire Stone Size Guide (Based on 6.5" Bracelet) Total Carat Weight ~15.5 ct tw Please note, kindly specify your bracelet size in the remarks when placing the order. If you have any special requests for this design (such as metal, gemstone, or design details), please contact our advisor for customization. Description Vivid and sophisticated, this colored gemstone bracelet showcases a striking 10×14mm oval lab orange sapphire , celebrated for its rich sunset-inspired hue and luminous brilliance. The elongated oval cut… | F27: 18K Gold | G27: Lab Grown Diamond | H27: 15.5 | I27: 15.5 ct | J27: 1.2mm round lab diamond DEF VVS-VS with 10*14mm oval lab sap | K27: 49124.8 | L27: =K27*(1-Pricing!$B$4) | M27: =L27*Pricing!$B$9*(1+Pricing!$B$6+Pricing!$B$7)+Pricing!$B$5 | N27: =M27*(1+Pricing!$B$8) | O27: =N27-M27 | P27: View Product | Q27: Fiorese Jewelry | R27: Open Image | S27: 1
A28: 25 | C28: Rose-Cut Lab Diamond Hook Earrings | D28: Earrings | E28: Stone Type: Lab Diamond Stone Spec: custom 5mm rose cut DEF VS If you have any special requests for this design (such as metal, gemstone, or design details), please contact our advisor for customization. Description Delicate and romantic, these hook earrings feature 5mm rose cut lab diamonds , known for their soft, domed facets and gentle, candlelit sparkle. The rose cut creates a subtle glow rather than sharp brilliance, giving the design a dreamy, antique-inspired feel. Suspended from a simple hook setting, the diamonds move gracefully with the wearer, catching light in a quiet, effortless… | F28: 18K Gold | G28: Lab Grown Diamond | I28: 5mm (per stone) | J28: 5mm rose cut DEF VS | K28: 968.24 | L28: =K28*(1-Pricing!$B$4) | M28: =L28*Pricing!$B$9*(1+Pricing!$B$6+Pricing!$B$7)+Pricing!$B$5 | N28: =M28*(1+Pricing!$B$8) | O28: =N28-M28 | P28: View Product | Q28: Fiorese Jewelry | R28: Open Image | S28: 1
A29: 26 | C29: Round-Cut Lab Diamond Halo Dangle Hook Earrings with Floating Center Stone | D29: Earrings | E29: Stone Type: Lab Diamond Center Stone: 5mm round cut DEF VS, about 1 ct tw Side Stone: 1.6mm round cut DEF VS, about 0.5 ct tw Height: 22.5mm Width: 11mm If you have any special requests for this design (such as metal, gemstone, or design details), please contact our advisor for customization. Description Elegant and full of movement, these hook earrings feature round-cut lab diamonds framed by a delicate halo setting , enhancing brilliance with a radiant circle of light. At the center, a movable diamond dangle adds graceful motion, allowing the stone to catch and reflect light from every… | F29: 18K Gold | G29: Lab Grown Diamond | H29: 0.5 | I29: 0.5 ct | J29: 2 pieces 0.5ct DEF VS + 30 pieces 1.6mm Round cut DEF VVS-VS | K29: 1425 | L29: =K29*(1-Pricing!$B$4) | M29: =L29*Pricing!$B$9*(1+Pricing!$B$6+Pricing!$B$7)+Pricing!$B$5 | N29: =M29*(1+Pricing!$B$8) | O29: =N29-M29 | P29: View Product | Q29: Fiorese Jewelry | R29: Open Image | S29: 1
A30: 27 | C30: Baguette- and Round-Cut Lab Diamond Ear Cuffs | D30: Earrings | E30: Stone Type: Lab Diamond Pave: 1.2mm round cut and 2*1.5mm baguette cut DEF VS, about 0.85 ct tw Inner Arc Length: 24.5mm Outer Arc Length: 31mm If you have any special requests for this design (such as metal, gemstone, or design details), please contact our advisor for customization. Description Modern and effortlessly chic, these ear cuffs feature a refined combination of baguette-cut and round-cut lab diamonds , creating a dynamic contrast of linear brilliance and soft sparkle. The mixed-cut design adds depth and dimension, wrapping the ear in a sleek, sculptural silhouette. Perfect for… | F30: 18K Gold | G30: Lab Grown Diamond | H30: 0.85 | I30: 0.85 ct | J30: 18 pieces 2*1.5mm Baguette cut + 50 pieces 1.2mm Round Cut D | K30: 2925.24 | L30: =K30*(1-Pricing!$B$4) | M30: =L30*Pricing!$B$9*(1+Pricing!$B$6+Pricing!$B$7)+Pricing!$B$5 | N30: =M30*(1+Pricing!$B$8) | O30: =N30-M30 | P30: View Product | Q30: Fiorese Jewelry | R30: Open Image | S30: 1
A31: 28 | C31: Round-Cut Lab Diamond Thin Eternity Ring | D31: Engagement Ring | E31: Stone Type: Lab Diamond Stone Spec: 1.3mm round cut DEF VS Band Width: 1.4mm Band Thickness: 1.6mm If you have any special requests for this design (such as metal, gemstone, or design details), please contact our advisor for customization. Description Delicate, refined, and effortlessly timeless, this thin eternity ring features a continuous circle of shimmering 1.3mm round-cut lab diamonds , creating a graceful ribbon of brilliance with understated sophistication. The slender silhouette offers a light, elegant presence that feels both modern and endlessly versatile. Each round diamond is… | F31: 18K Gold | G31: Lab Grown Diamond | I31: 1.3mm (per stone) | J31: 1.3mm Round Cut DEF VS | K31: 894.75 | L31: =K31*(1-Pricing!$B$4) | M31: =L31*Pricing!$B$9*(1+Pricing!$B$6+Pricing!$B$7)+Pricing!$B$5 | N31: =M31*(1+Pricing!$B$8) | O31: =N31-M31 | P31: View Product | Q31: Fiorese Jewelry | R31: Open Image | S31: 1
A32: 29 | C32: Heart-Cut Lab Diamond Solitaire Ring with Martini Setting | D32: Engagement Ring | E32: Stone Type: Lab Diamond Center Stone: 0.25ct heart cut DEF VS about Band Width: 1.3mm Band Thickness: 1.3mm If you have any special requests for this design (such as metal, gemstone, or design details), please contact our advisor for customization. Description Romantic yet refined, this heart-cut lab diamond solitaire ring features a delicate 3-prong martini setting paired with a sleek slim band , creating a design that feels both meaningful and effortlessly wearable. The martini-style base allows the diamond to sit low on the finger, giving the center stone a subtle floating appearance… | F32: 18K Gold | G32: Lab Grown Diamond | H32: 0.25 | I32: 0.25 ct | J32: 0.25ct heart cut DEF VS | K32: 1024.5 | L32: =K32*(1-Pricing!$B$4) | M32: =L32*Pricing!$B$9*(1+Pricing!$B$6+Pricing!$B$7)+Pricing!$B$5 | N32: =M32*(1+Pricing!$B$8) | O32: =N32-M32 | P32: View Product | Q32: Fiorese Jewelry | R32: Open Image | S32: 1
A33: 30 | C33: Fancy Pink Round Lab Diamond Slim Eternity Ring | D33: Engagement Ring | E33: Stone Type: Lab Diamond Stone Spec: 1.3mm round cut fancy pink VS Band Width: 1.5mm Band Thickness: 1.6mm If you have any special requests for this design (such as metal, gemstone, or design details), please contact our advisor for customization. Description Romantic, delicate, and effortlessly refined, this slim eternity ring features a continuous circle of luminous 1.3mm fancy pink round lab diamonds , creating a graceful ribbon of soft blush brilliance around the finger. The slender silhouette offers understated elegance while adding a subtle touch of rare color and feminine… | F33: 18K Gold | G33: Lab Grown Diamond | I33: 1.3mm (per stone) | J33: 1.3mm Fancy Pink Round Lab Diamond VS | K33: 1053.75 | L33: =K33*(1-Pricing!$B$4) | M33: =L33*Pricing!$B$9*(1+Pricing!$B$6+Pricing!$B$7)+Pricing!$B$5 | N33: =M33*(1+Pricing!$B$8) | O33: =N33-M33 | P33: View Product | Q33: Fiorese Jewelry | R33: Open Image | S33: 1
A34: 31 | C34: Round Lab Diamond Half Eternity Ring with Marquise-Shaped Millegrain Design | D34: Engagement Ring | E34: Stone Type: Lab Diamond Stone Spec: round cut DEF VS about 0.16 ct tw Band Width: 2mm Band Thickness: 1.5mm If you have any special requests for this design (such as metal, gemstone, or design details), please contact our advisor for customization. Description Romantic, intricate, and timelessly refined, this half eternity ring features shimmering round lab diamonds framed within elegant marquise-shaped millegrain detailing , creating a graceful composition inspired by antique fine jewelry artistry. The delicate marquise motifs introduce soft vintage character and refined architectural… | F34: 18K Gold | G34: Lab Grown Diamond | H34: 0.16 | I34: 0.16 ct | J34: 12 pieces of 1.5mm round cut DEF VS | K34: 1266.75 | L34: =K34*(1-Pricing!$B$4) | M34: =L34*Pricing!$B$9*(1+Pricing!$B$6+Pricing!$B$7)+Pricing!$B$5 | N34: =M34*(1+Pricing!$B$8) | O34: =N34-M34 | P34: View Product | Q34: Fiorese Jewelry | R34: Open Image | S34: 1
A35: 32 | C35: Round Lab Diamond Twist Ring Enhancer with Pavé | D35: Engagement Ring | E35: Stone Type: Lab Diamond Stone Spec: round cut DEF VS Band Width: 1.8mm Band Thickness: 1.8mm If you have any special requests for this design (such as metal, gemstone, or design details), please contact our advisor for customization. Description Elegant, romantic, and beautifully fluid, this ring enhancer features shimmering round lab diamonds woven through an intricate intertwined pavé band design , creating a graceful twisting silhouette filled with movement and brilliance. The sculptural curves wrap delicately around an engagement ring, adding layered sparkle and refined dimensional… | F35: 18K Gold | G35: Lab Grown Diamond | I35: 1.8mm (per stone) | J35: round cut DEF VS | K35: 1311.75 | L35: =K35*(1-Pricing!$B$4) | M35: =L35*Pricing!$B$9*(1+Pricing!$B$6+Pricing!$B$7)+Pricing!$B$5 | N35: =M35*(1+Pricing!$B$8) | O35: =N35-M35 | P35: View Product | Q35: Fiorese Jewelry | R35: Open Image | S35: 1
A36: 33 | C36: Round Lab Diamond V-Shaped Wedding Ring with Millegrain Micropavé | D36: Engagement Ring | E36: Stone Type: Lab Diamond Stone Spec: round cut DEF VS Band Width: 1.7mm Band Thickness: 1.5mm If you have any special requests for this design (such as metal, gemstone, or design details), please contact our advisor for customization. Description Romantic, refined, and intricately detailed, this V-shaped wedding ring features shimmering round lab diamonds accented by delicate millegrain micropavé craftsmanship , creating a graceful balance of vintage-inspired elegance and modern bridal sophistication. The contoured silhouette is designed to complement engagement rings beautifully while adding… | F36: 18K Gold | G36: Lab Grown Diamond | I36: 1.7mm (per stone) | J36: 21 pieces of round lab diamond DEF VS | K36: 1333.5 | L36: =K36*(1-Pricing!$B$4) | M36: =L36*Pricing!$B$9*(1+Pricing!$B$6+Pricing!$B$7)+Pricing!$B$5 | N36: =M36*(1+Pricing!$B$8) | O36: =N36-M36 | P36: View Product | Q36: Fiorese Jewelry | R36: Open Image | S36: 1
A37: 34 | C37: Round-Cut Lab Diamond V-Shaped Wedding Ring Enhancer with French Pavé | D37: Engagement Ring | E37: Stone Type: Lab Diamond Stone Spec: 1.8mm round cut DEF VS (3/4 pave ) Band Width: 2.3mm Band Thickness: from 2.5mm to 1.9mm If you have any special requests for this design (such as metal, gemstone, or design details), please contact our advisor for customization. Description Elegant, radiant, and beautifully sculptural, this wedding ring enhancer features shimmering round-cut lab diamonds set in refined French pavé detailing along a graceful V-shaped silhouette . Designed to contour elegantly around an engagement ring, the enhancer creates a luminous layered look filled with timeless… | F37: 18K Gold | G37: Lab Grown Diamond | I37: 1.8mm (per stone) | J37: 1.8mm round cut DEF VS | K37: 1401 | L37: =K37*(1-Pricing!$B$4) | M37: =L37*Pricing!$B$9*(1+Pricing!$B$6+Pricing!$B$7)+Pricing!$B$5 | N37: =M37*(1+Pricing!$B$8) | O37: =N37-M37 | P37: View Product | Q37: Fiorese Jewelry | R37: Open Image | S37: 1
A38: 35 | C38: Round & Marquise-Cut Lab Diamond Eternity Ring with Shared-Prong Setting | D38: Engagement Ring | E38: Stone Type: Lab Diamond Stone Spec: 2mm round cut and 4*2mm marquise cut DEF VS If you have any special requests for this design (such as metal, gemstone, or design details), please contact our advisor for customization. Description Elegant, romantic, and beautifully distinctive, this eternity ring features an alternating arrangement of round and marquise-cut lab diamonds secured in refined shared-prong settings , creating a graceful rhythm of brilliance and elongated elegance around the finger. The combination of diamond shapes evokes the beauty of blooming petals and delicate leaf motifs… | F38: 18K Gold | G38: Lab Grown Diamond | I38: 4×2mm (per stone) | J38: 2mm Round Cut and 4*2mm Marquise Cut DEF VS | K38: 1414.5 | L38: =K38*(1-Pricing!$B$4) | M38: =L38*Pricing!$B$9*(1+Pricing!$B$6+Pricing!$B$7)+Pricing!$B$5 | N38: =M38*(1+Pricing!$B$8) | O38: =N38-M38 | P38: View Product | Q38: Fiorese Jewelry | R38: Open Image | S38: 1
A39: 36 | C39: Round-Cut Lab Diamond V-Shaped Wedding Ring Enhancer with U-Shaped Pavé | D39: Engagement Ring | E39: Stone Type: Lab Diamond Stone Spec: 1.9mm round cut DEF VS (half eternity ) Band Width: 2mm Band Thickness: From 2mm to 1.5mm If you have any special requests for this design (such as metal, gemstone, or design details), please contact our advisor for customization. Description Elegant, luminous, and beautifully sculptural, this wedding ring enhancer features shimmering round-cut lab diamonds set within a refined U-shaped pavé design , forming a graceful V-shaped silhouette that contours elegantly around an engagement ring. The flowing shape enhances the center ring with added brilliance,… | F39: 18K Gold | G39: Lab Grown Diamond | I39: 1.9mm (per stone) | J39: 1.9mm round cut DEF VS | K39: 1485.75 | L39: =K39*(1-Pricing!$B$4) | M39: =L39*Pricing!$B$9*(1+Pricing!$B$6+Pricing!$B$7)+Pricing!$B$5 | N39: =M39*(1+Pricing!$B$8) | O39: =N39-M39 | P39: View Product | Q39: Fiorese Jewelry | R39: Open Image | S39: 1
A40: 37 | C40: Asscher-Cut Lab Diamond 7-Stone Half Eternity Ring with Bezel | D40: Engagement Ring | E40: Stone Type: Lab Diamond Stone Spec: 2.5*2.5mm asscher cut DEF VS Band Width: 1.8mm Band Thickness: 1.8mm If you have any special requests for this design (such as metal, gemstone, or design details), please contact our advisor for customization. Description Elegant, bold, and impeccably refined, this 7-stone half eternity ring features luminous Asscher-cut lab diamonds framed within sleek bezel settings , creating a sophisticated composition inspired by timeless Art Deco glamour. The Asscher cuts showcase crisp geometric symmetry and mesmerizing step-cut reflections, delivering understated… | F40: 18K Gold | G40: Lab Grown Diamond | I40: 2.5×2.5mm (per stone) | J40: 7 pieces of 2.5*2.5mm Asscher Cut DEF VS | K40: 1551.75 | L40: =K40*(1-Pricing!$B$4) | M40: =L40*Pricing!$B$9*(1+Pricing!$B$6+Pricing!$B$7)+Pricing!$B$5 | N40: =M40*(1+Pricing!$B$8) | O40: =N40-M40 | P40: View Product | Q40: Fiorese Jewelry | R40: Open Image | S40: 2
A41: 38 | C41: Baguette-Cut Lab Diamond 7-Stone Half Eternity Ring | D41: Engagement Ring | E41: Stone Spec: 7 pieces of 3*1.5mm baguette cut lab diamond DEF VS Band Width: 2mm Band Thickness: 1.8mm If you have any special requests for this design (such as metal, gemstone, or design details), please contact our advisor for customization. Description Modern, sculptural, and elegantly refined, this 7-stone half eternity ring features luminous baguette-cut lab diamonds arranged in a graceful wave-inspired design , creating a fluid balance between geometric precision and organic movement. The sleek baguette cuts deliver crisp linear reflections with understated sophistication and… | F41: 18K Gold | G41: Lab Grown Diamond | I41: 3×1.5mm (per stone) | J41: 7 pieces of 3*1.5 mm Baguette Cut DEF VVS-VS | K41: 1596.75 | L41: =K41*(1-Pricing!$B$4) | M41: =L41*Pricing!$B$9*(1+Pricing!$B$6+Pricing!$B$7)+Pricing!$B$5 | N41: =M41*(1+Pricing!$B$8) | O41: =N41-M41 | P41: View Product | Q41: Fiorese Jewelry | R41: Open Image | S41: 1
A42: 39 | C42: 2mm Round Lab Diamond Bezel Eternity Ring | D42: Engagement Ring | E42: Stone Type: Lab Diamond Stone Spec: 2mm round cut DEF VS If you have any special requests for this design (such as metal, gemstone, or design details), please contact our advisor for customization. Description Elegant, refined, and effortlessly timeless, this eternity ring features a continuous circle of shimmering 2mm round lab diamonds framed within sleek bezel settings , crafted in luminous 14K yellow gold for a warm and sophisticated finish. The classic round diamonds radiate exceptional brilliance, creating a delicate ribbon of light around the finger with understated luxury appeal.… | F42: 18K Gold | G42: Lab Grown Diamond | I42: 2mm (per stone) | J42: 2mm Round cut DEF VS | K42: 1664.25 | L42: =K42*(1-Pricing!$B$4) | M42: =L42*Pricing!$B$9*(1+Pricing!$B$6+Pricing!$B$7)+Pricing!$B$5 | N42: =M42*(1+Pricing!$B$8) | O42: =N42-M42 | P42: View Product | Q42: Fiorese Jewelry | R42: Open Image | S42: 1
A43: 40 | C43: Heart Shaped Lab Diamond 5-Stone Bezel Half Eternity Ring | D43: Engagement Ring | E43: Stone Type: Lab Diamond Stone Spec: heart cut DEF VS Band Width: 2.2mm Band Thickness: 1.8mm If you have any special requests for this design (such as metal, gemstone, or design details), please contact our advisor for customization. Description Romantic, elegant, and beautifully expressive, this 5-stone half eternity ring features luminous 4×4mm heart-shaped lab diamonds framed within refined bezel settings , creating a timeless symbol of love and devotion with elevated modern sophistication. The heart-shaped diamonds add soft feminine charm while radiating exceptional brilliance from every… | F43: 18K Gold | G43: Lab Grown Diamond | I43: 3×3mm (per stone) | J43: 7 pieces of 3*3mm Heart Cut DEF VS | K43: 1724.25 | L43: =K43*(1-Pricing!$B$4) | M43: =L43*Pricing!$B$9*(1+Pricing!$B$6+Pricing!$B$7)+Pricing!$B$5 | N43: =M43*(1+Pricing!$B$8) | O43: =N43-M43 | P43: View Product | Q43: Fiorese Jewelry | R43: Open Image | S43: 2
A44: 41 | C44: Round Brilliant Lab Diamond Wedding Ring Enhancer with French Pavé Ribbon Design | D44: Engagement Ring | E44: Stone Type: Lab Diamond Stone Spec: round cut DEF VS (2/3 circle of pave) Band Width: 2.5mm Band Thickness: 2mm If you have any special requests for this design (such as metal, gemstone, or design details), please contact our advisor for customization. Description Elegant, graceful, and beautifully sculptural, this wedding ring enhancer features shimmering round brilliant lab diamonds set in refined French pavé detailing , flowing through an intricate ribbon-inspired design that wraps the finger with luminous sophistication. The fluid silhouette evokes the softness and movement of finely… | F44: 18K Gold | G44: Lab Grown Diamond | I44: 2.5mm (per stone) | J44: round cut DEF VS | K44: 1726.5 | L44: =K44*(1-Pricing!$B$4) | M44: =L44*Pricing!$B$9*(1+Pricing!$B$6+Pricing!$B$7)+Pricing!$B$5 | N44: =M44*(1+Pricing!$B$8) | O44: =N44-M44 | P44: View Product | Q44: Fiorese Jewelry | R44: Open Image | S44: 1
A45: 42 | C45: Round-Cut Lab Diamond Eternity Ring with Shared Round Prong | D45: Engagement Ring | E45: Stone Type: Lab Diamond Stone Spec: 2.5mm round cut DEF VS If you have any special requests for this design (such as metal, gemstone, or design details), please contact our advisor for customization. Description Timeless, radiant, and effortlessly elegant, this eternity ring features a continuous circle of shimmering round-cut lab diamonds secured in refined shared round prong settings . The classic round diamonds maximize fire and brilliance, creating an uninterrupted ribbon of light that sparkles beautifully from every angle. The delicate shared round prongs minimize visible metal while… | F45: 18K Gold | G45: Lab Grown Diamond | I45: 2.5mm (per stone) | J45: 2.5mm round cut DEF VS | K45: 1754.25 | L45: =K45*(1-Pricing!$B$4) | M45: =L45*Pricing!$B$9*(1+Pricing!$B$6+Pricing!$B$7)+Pricing!$B$5 | N45: =M45*(1+Pricing!$B$8) | O45: =N45-M45 | P45: View Product | Q45: Fiorese Jewelry | R45: Open Image | S45: 1
A46: 43 | C46: Round & Marquise-Cut Lab Diamond Eternity Ring with Millegrain Bezel | D46: Engagement Ring | E46: Stone Type: Lab Diamond Stone Spec: round cut and marquise cut DEF VS Band Width: 3mm Band Thickness: 2mm If you have any special requests for this design (such as metal, gemstone, or design details), please contact our advisor for customization. Description Romantic, intricate, and timelessly refined, this eternity ring features an alternating arrangement of round and marquise-cut lab diamonds framed within elegant millegrain bezel settings , creating a graceful composition inspired by antique floral motifs and heirloom fine jewelry artistry. The combination of soft round brilliance and… | F46: 18K Gold | G46: Lab Grown Diamond | I46: 4×2mm (per stone) | J46: 2mm Round Cut and 4*2mm Marquise Cut DEF VS | K46: 1761.75 | L46: =K46*(1-Pricing!$B$4) | M46: =L46*Pricing!$B$9*(1+Pricing!$B$6+Pricing!$B$7)+Pricing!$B$5 | N46: =M46*(1+Pricing!$B$8) | O46: =N46-M46 | P46: View Product | Q46: Fiorese Jewelry | R46: Open Image | S46: 1
... A51: 48 | C51: Heart-Shaped Lab Diamond Eternity Ring with Three-Claw Basket Setting | D51: Engagement Ring | E51: Stone Type: Lab Diamond Stone Spec: 3*3mm heart cut DEF VS If you have any special requests for this design (such as metal, gemstone, or design details), please contact our advisor for customization. Description Romantic, radiant, and endlessly elegant, this eternity ring features a continuous circle of 3×3mm heart-shaped lab diamonds secured in delicate three-claw prong basket settings , crafted in luxurious platinum . The graceful heart silhouettes symbolize love, devotion, and enduring connection, transforming this classic eternity band into a meaningful expression of romance. Each… | F51: 18K Gold | G51: Lab Grown Diamond | I51: 3×3mm (per stone) | J51: 3*3mm Heart Cut DEF VS | K51: 1848.75 | L51: =K51*(1-Pricing!$B$4) | M51: =L51*Pricing!$B$9*(1+Pricing!$B$6+Pricing!$B$7)+Pricing!$B$5 | N51: =M51*(1+Pricing!$B$8) | O51: =N51-M51 | P51: View Product | Q51: Fiorese Jewelry | R51: Open Image | S51: 2
A52: 49 | C52: Asscher-Cut Lab Diamond Bezel Solitaire Ring with Floating Setting | D52: Engagement Ring | E52: Stone Type: Lab Diamond Center Stone: 1ct asscher cut DEF VS Band Width: 1.8mm Band Thickness: 1.8mm If you have any special requests for this design (such as metal, gemstone, or design details), please contact our advisor for customization. Description Sleek and architectural, this ring features an Asscher-cut lab diamond secured in a smooth bezel setting , highlighting its crisp step-cut geometry. The elevated floating design lifts the stone subtly above the band, enhancing light flow and creating a refined sense of dimension. With its minimalist silhouette , this piece emphasizes clarity,… | F52: 18K Gold | G52: Lab Grown Diamond | H52: 1 | I52: 1 ct | J52: 1ct Asscher Cut Lab Diamond DEF VS | K52: 1866.75 | L52: =K52*(1-Pricing!$B$4) | M52: =L52*Pricing!$B$9*(1+Pricing!$B$6+Pricing!$B$7)+Pricing!$B$5 | N52: =M52*(1+Pricing!$B$8) | O52: =N52-M52 | P52: View Product | Q52: Fiorese Jewelry | R52: Open Image | S52: 1
A53: 50 | C53: Oval-Cut Lab Diamond Ring with Cathedral Setting and Tapered Band | D53: Engagement Ring | E53: Stone Type: Lab Diamond Center Stone: 1ct oval cut DEF VS Band Width: 2.3mm Band Thickness: 1.5mm If you have any special requests for this design (such as metal, gemstone, or design details), please contact our advisor for customization. Description Balanced and refined, this oval-cut lab diamond cathedral setting ring features a distinctive double-claw prong design paired with a gently tapered band , creating a silhouette that feels both structured and graceful. The cathedral shoulders rise smoothly to support the center stone, elevating it above the band to enhance light performance and… | F53: 18K Gold | G53: Lab Grown Diamond | H53: 1 | I53: 1 ct | J53: 1ct oval cut DEF VS | K53: 1866.75 | L53: =K53*(1-Pricing!$B$4) | M53: =L53*Pricing!$B$9*(1+Pricing!$B$6+Pricing!$B$7)+Pricing!$B$5 | N53: =M53*(1+Pricing!$B$8) | O53: =N53-M53 | P53: View Product | Q53: Fiorese Jewelry | R53: Open Image | S53: 1
A54: 51 | C54: Asscher-Cut Lab Diamond Eternity Ring with Millegrain Bezel | D54: Engagement Ring | E54: Stone Type: Lab Diamond Stone Spec: 2.5*2.5mm asscher cut DEF VS Band Width: 3.5mm Band Thickness: 2.5mm If you have any special requests for this design (such as metal, gemstone, or design details), please contact our advisor for customization. Description Elegant, architectural, and richly heirloom-inspired, this eternity ring features a continuous circle of luminous Asscher-cut lab diamonds framed within intricate millegrain bezel settings . Renowned for their crisp symmetry and mesmerizing hall-of-mirrors reflections, Asscher-cut diamonds bring timeless Art Deco sophistication and… | F54: 18K Gold | G54: Lab Grown Diamond | I54: 2.5×2.5mm (per stone) | J54: 2.5*2.5mm Asscher Cut DEF VS | K54: 1926 | L54: =K54*(1-Pricing!$B$4) | M54: =L54*Pricing!$B$9*(1+Pricing!$B$6+Pricing!$B$7)+Pricing!$B$5 | N54: =M54*(1+Pricing!$B$8) | O54: =N54-M54 | P54: View Product | Q54: Fiorese Jewelry | R54: Open Image | S54: 1
A55: 52 | C55: Round Lab Diamond Wedding Ring with Lace Design | D55: Engagement Ring | E55: Stone Type: Lab Diamond Stone Spec: 2mm round cut DEF VS about 1.41 ct tw Band Width: 3.3mm Band Thickness: 1.5mm If you have any special requests for this design (such as metal, gemstone, or design details), please contact our advisor for customization. Description Delicate, romantic, and beautifully intricate, this wedding ring features shimmering round lab diamonds woven into an elegant lace-inspired design , capturing the softness and artistry of fine vintage lacework through refined fine jewelry craftsmanship. The graceful openwork silhouette creates airy texture and timeless feminine… | F55: 18K Gold | G55: Lab Grown Diamond | H55: 1.41 | I55: 1.41 ct | J55: 47 pieces of 2mm round cut DEF VS | K55: 1926 | L55: =K55*(1-Pricing!$B$4) | M55: =L55*Pricing!$B$9*(1+Pricing!$B$6+Pricing!$B$7)+Pricing!$B$5 | N55: =M55*(1+Pricing!$B$8) | O55: =N55-M55 | P55: View Product | Q55: Fiorese Jewelry | R55: Open Image | S55: 1
A56: 53 | C56: Cushion-Cut Lab Diamond 7-Stone Half Eternity Ring | D56: Engagement Ring | E56: Stone Type: Lab Diamond Stone Spec: 3*3mm cushion cut DEF VS Band Width: 2mm Band Thickness: 1.8mm If you have any special requests for this design (such as metal, gemstone, or design details), please contact our advisor for customization. Description Elegant proportions and timeless brilliance define this 14K yellow gold 7-stone ring, featuring seven perfectly matched 3×3mm cushion-cut lab-grown diamonds. Combining the soft outline of a cushion cut with exceptional brilliance, each diamond offers a romantic balance of classic sparkle and contemporary refinement. The seven-stone arrangement… | F56: 18K Gold | G56: Lab Grown Diamond | I56: 3×3mm (per stone) | J56: 3*3mm Cushion Cut DEF VS | K56: 1933.5 | L56: =K56*(1-Pricing!$B$4) | M56: =L56*Pricing!$B$9*(1+Pricing!$B$6+Pricing!$B$7)+Pricing!$B$5 | N56: =M56*(1+Pricing!$B$8) | O56: =N56-M56 | P56: View Product | Q56: Fiorese Jewelry | R56: Open Image | S56: 1
A57: 54 | C57: Oval Old Mine-Cut Brown Lab Diamond Solitaire Ring with Cathedral Setting | D57: Engagement Ring | E57: Stone Type: Lab Diamond Center Stone: custom 1ct oval old mine cut brown VS Band Width: 1.8mm Band Thickness: 1.8mm If you have any special requests for this design (such as metal, gemstone, or design details), please contact our advisor for customization. Description Distinctive and elegantly structured, this oval Old Mine-cut brown lab diamond solitaire ring features a refined 6-claw cathedral setting combined with a floating head design and a split tapered band for a balanced, dimensional silhouette. The cathedral shoulders rise smoothly from the band, lifting the center stone into an… | F57: 18K Gold | G57: Lab Grown Diamond | H57: 1 | I57: 1 ct | J57: 1ct Oval Old Mine Cut Brown VS | K57: 1934.25 | L57: =K57*(1-Pricing!$B$4) | M57: =L57*Pricing!$B$9*(1+Pricing!$B$6+Pricing!$B$7)+Pricing!$B$5 | N57: =M57*(1+Pricing!$B$8) | O57: =N57-M57 | P57: View Product | Q57: Fiorese Jewelry | R57: Open Image | S57: 1
A58: 55 | C58: Old European-Cut Lab Diamond 7-Stone Half Eternity Ring with Tapered Band | D58: Engagement Ring | E58: Stone Type: Lab Diamond Stone Spec: custom 3.5mm old European cut DEF VS Band Width: 2.2mm Band Thickness: 1.5mm If you have any special requests for this design (such as metal, gemstone, or design details), please contact our advisor for customization. Description Romantic, timeless, and richly refined, this 7-stone half eternity ring features luminous 3.5mm old European-cut lab diamonds arranged in an elegant row that celebrates antique-inspired brilliance and heirloom sophistication. Known for their broad vintage facets and soft candlelit sparkle, old European cuts radiate warmth, depth,… | F58: 18K Gold | G58: Lab Grown Diamond | I58: 3.5mm (per stone) | J58: 7 pieces of 3.5mm old European cut DEF VS | K58: 1939.5 | L58: =K58*(1-Pricing!$B$4) | M58: =L58*Pricing!$B$9*(1+Pricing!$B$6+Pricing!$B$7)+Pricing!$B$5 | N58: =M58*(1+Pricing!$B$8) | O58: =N58-M58 | P58: View Product | Q58: Fiorese Jewelry | R58: Open Image | S58: 1
A59: 56 | C59: Round Diamond Bezel Ring with J Initial-Inspired Design | D59: Engagement Ring | E59: Stone Type: Lab Diamond Pave: round cut DEF VVS-VS Band Width: 2.3mm Band Thickness: 1.4mm If you have any special requests for this design (such as metal, gemstone, or design details), please contact our advisor for customization. Description Personal and modern, this ring features a round diamond secured in a sleek bezel setting , integrated into a refined “J” initial-inspired design . The clean silhouette highlights the diamond’s soft brilliance while the sculptural form adds a meaningful, customized touch. Perfect for those who appreciate personalized jewelry with minimalist elegance ,… | F59: 18K Gold | G59: Lab Grown Diamond | I59: 2.3mm (per stone) | J59: Round Lab Diamond DEF VVS-VS | K59: 1967.25 | L59: =K59*(1-Pricing!$B$4) | M59: =L59*Pricing!$B$9*(1+Pricing!$B$6+Pricing!$B$7)+Pricing!$B$5 | N59: =M59*(1+Pricing!$B$8) | O59: =N59-M59 | P59: View Product | Q59: Fiorese Jewelry | R59: Open Image | S59: 1
A60: 57 | C60: Round & Radiant-Cut Lab Diamond 5-Stone Half Eternity Ring | D60: Engagement Ring | E60: Stone Type: Lab Diamond Stone Spec: round cut and radiant cut DEF VS Band Width: 2mm Band Thickness: 1.8mm If you have any special requests for this design (such as metal, gemstone, or design details), please contact our advisor for customization. Description Distinctive, radiant, and beautifully balanced, this 5-stone half eternity ring features an elegant alternating arrangement of round and radiant-cut lab diamonds , creating a striking interplay of soft brilliance and geometric sparkle. The contrasting diamond shapes bring depth, movement, and contemporary sophistication to the design… | F60: 18K Gold | G60: Lab Grown Diamond | I60: 3×5mm (per stone) | J60: 3 pieces of 3mm round cut + 2 pieces of 3*5mm radiant cut DE | K60: 2004.75 | L60: =K60*(1-Pricing!$B$4) | M60: =L60*Pricing!$B$9*(1+Pricing!$B$6+Pricing!$B$7)+Pricing!$B$5 | N60: =M60*(1+Pricing!$B$8) | O60: =N60-M60 | P60: View Product | Q60: Fiorese Jewelry | R60: Open Image | S60: 1
A61: 58 | C61: Heart-Shaped Lab Diamond Two-Tone Bezel Solitaire Ring with Slim Band | D61: Engagement Ring | E61: Stone Type: Lab Diamond Center Stone: 1ct heart cut DEF VS Band Width: 1.6mm Band Thickness: 1.6mm If you have any special requests for this design (such as metal, gemstone, or design details), please contact our advisor for customization. Description Sweet and modern, this ring features a heart-shaped lab diamond secured in a sleek two-tone bezel setting , creating a beautiful contrast that highlights the stone’s romantic silhouette. The slim band enhances its delicate profile, offering a lightweight and elegant feel on the hand. Perfect for those who appreciate romantic symbolism with… | F61: 18K Yellow Gold | G61: Lab Grown Diamond | H61: 1 | I61: 1 ct | J61: 1ct heart cut DEF VS | K61: 2016.75 | L61: =K61*(1-Pricing!$B$4) | M61: =L61*Pricing!$B$9*(1+Pricing!$B$6+Pricing!$B$7)+Pricing!$B$5 | N61: =M61*(1+Pricing!$B$8) | O61: =N61-M61 | P61: View Product | Q61: Fiorese Jewelry | R61: Open Image | S61: 1
A62: 59 | C62: Radiant-Cut Lab Diamond Bezel Solitaire Ring with Basket Setting | D62: Engagement Ring | E62: Stone Type: Lab Diamond Center Stone: 1.5ct radiant cut DEF VS Band Width: 1.8mm Band Thickness: 1.8mm If you have any special requests for this design (such as metal, gemstone, or design details), please contact our advisor for customization. Description Sleek and contemporary, this solitaire ring features a radiant-cut lab diamond secured in a refined bezel-set basket setting , allowing light to enhance its vibrant brilliance. The minimalist design emphasizes clean lines and balanced proportions, creating a modern silhouette that feels both effortless and sophisticated. Perfect for those… | F62: 18K Gold | G62: Lab Grown Diamond | H62: 1.5 | I62: 1.5 ct | J62: 1.5ct Radiant Cut Lab Diamond DEF VS | K62: 2035.5 | L62: =K62*(1-Pricing!$B$4) | M62: =L62*Pricing!$B$9*(1+Pricing!$B$6+Pricing!$B$7)+Pricing!$B$5 | N62: =M62*(1+Pricing!$B$8) | O62: =N62-M62 | P62: View Product | Q62: Fiorese Jewelry | R62: Open Image | S62: 1
A63: 60 | C63: Heart-Shaped Lab Diamond Eternity Ring with Bezel Basket | D63: Engagement Ring | E63: Stone Type: Lab Diamond Stone Spec: 3*3mm heart cut DEF VS Band Width: 4mm Band Thickness: 2.2mm If you have any special requests for this design (such as metal, gemstone, or design details), please contact our advisor for customization. Description Romantic, radiant, and delicately refined, this eternity ring features a continuous circle of luminous 3×3mm heart-shaped lab diamonds secured in elegant bezel basket settings . The symbolic heart silhouettes create a graceful expression of love and devotion while adding playful sophistication and timeless brilliance to the design. Each… | F63: 18K Gold | G63: Lab Grown Diamond | I63: 3×3mm (per stone) | J63: 3*3mm Heart Cut DEF VS | K63: 2039.25 | L63: =K63*(1-Pricing!$B$4) | M63: =L63*Pricing!$B$9*(1+Pricing!$B$6+Pricing!$B$7)+Pricing!$B$5 | N63: =M63*(1+Pricing!$B$8) | O63: =N63-M63 | P63: View Product | Q63: Fiorese Jewelry | R63: Open Image | S63: 1
A64: 61 | C64: Heart-Shaped Lab Diamond East-West Bezel Eternity Ring | D64: Engagement Ring | E64: Stone Type: Lab Diamond Stone Spec: 3*3mm heart cut DEF VS If you have any special requests for this design (such as metal, gemstone, or design details), please contact our advisor for customization. Description Romantic, contemporary, and effortlessly refined, this eternity ring features a continuous circle of 3×3mm heart-shaped lab diamonds set in sleek bezel settings and arranged in a distinctive east-west orientation , crafted in luminous 14K white gold . The modern horizontal placement offers a fresh interpretation of the classic heart motif while preserving its timeless symbolism of… | F64: 18K Gold | G64: Lab Grown Diamond | I64: 3×3mm (per stone) | J64: 3*3mm Heart Cut DEF VS | K64: 2040 | L64: =K64*(1-Pricing!$B$4) | M64: =L64*Pricing!$B$9*(1+Pricing!$B$6+Pricing!$B$7)+Pricing!$B$5 | N64: =M64*(1+Pricing!$B$8) | O64: =N64-M64 | P64: View Product | Q64: Fiorese Jewelry | R64: Open Image | S64: 1
A65: 62 | C65: Round-Cut Lab Diamond Eternity Ring with Millegrain Floral Band | D65: Engagement Ring | E65: Stone Type: Lab Diamond Stone Spec: round cut DEF VS from 2mm to 1.3mm (half eternity) Band Width: 2.5mm Band Thickness: 1.8mm If you have any special requests for this design (such as metal, gemstone, or design details), please contact our advisor for customization. Description Romantic, intricate, and timelessly elegant, this eternity ring features shimmering round-cut lab diamonds accented by delicate millegrain detailing and an ornate floral-inspired band design . Inspired by antique fine jewelry artistry, the ring captures the charm of heirloom craftsmanship with refined modern… | F65: 18K Gold | G65: Lab Grown Diamond | I65: 2mm (per stone) | J65: Round Cut DEF VS | K65: 2052 | L65: =K65*(1-Pricing!$B$4) | M65: =L65*Pricing!$B$9*(1+Pricing!$B$6+Pricing!$B$7)+Pricing!$B$5 | N65: =M65*(1+Pricing!$B$8) | O65: =N65-M65 | P65: View Product | Q65: Fiorese Jewelry | R65: Open Image | S65: 1
A66: 63 | C66: Emerald-Cut Lab Diamond Five-Stone Ring with Basket Setting and Baguette Side Stones | D66: Engagement Ring | E66: Stone Type: Lab Diamond Center Stone: 1ct emerald cut DEF VS Side Stone: baguette cut DEF VS Band Width: 2mm Band Thickness: 1.8mm If you have any special requests for this design (such as metal, gemstone, or design details), please contact our advisor for customization. Description Refined and elegantly structured, this five-stone ring features a crisp 1ct emerald-cut lab diamond at its center, secured in a classic four-round-prong basket setting that enhances light flow and showcases its step-cut clarity. On each side, baguette-cut lab diamond accents with subtle half-bezel detailing add… | F66: 18K Gold | G66: Lab Grown Diamond | H66: 1 | I66: 1 ct | J66: 1ct Emerald Cut Lab Diamond DEF VS | K66: 2061.75 | L66: =K66*(1-Pricing!$B$4) | M66: =L66*Pricing!$B$9*(1+Pricing!$B$6+Pricing!$B$7)+Pricing!$B$5 | N66: =M66*(1+Pricing!$B$8) | O66: =N66-M66 | P66: View Product | Q66: Fiorese Jewelry | R66: Open Image | S66: 1
A67: 64 | C67: Cushion-Cut Lab Diamond Bezel Solitaire Ring | D67: Engagement Ring | E67: Stone Type: Lab Diamond Center Stone: 1ct cushion cut DEF VS Band Width: 2.2mm Band Thickness: 1.8mm If you have any special requests for this design (such as metal, gemstone, or design details), please contact our advisor for customization. Description Timeless and gracefully structured, this solitaire ring features a cushion-cut lab diamond secured in a smooth bezel setting , highlighting its soft edges and radiant sparkle. The cathedral design lifts the center stone for added presence and light, while the tapered band enhances balance and draws focus to the diamond. Perfect for those who… | F67: 18K Gold | G67: Lab Grown Diamond | H67: 1 | I67: 1 ct | J67: 1ct Cushion cut DEF VS | K67: 2086.5 | L67: =K67*(1-Pricing!$B$4) | M67: =L67*Pricing!$B$9*(1+Pricing!$B$6+Pricing!$B$7)+Pricing!$B$5 | N67: =M67*(1+Pricing!$B$8) | O67: =N67-M67 | P67: View Product | Q67: Fiorese Jewelry | R67: Open Image | S67: 1
A68: 65 | C68: Emerald-Cut Lab Diamond East-West Bezel Solitaire Ring | D68: Engagement Ring | E68: Stone Type: Lab Diamond Center Stone: 2ct emerald cut DEF VS Band Width: 1.8mm Band Thickness: 1.5mm If you have any special requests for this design (such as metal, gemstone, or design details), please contact our advisor for customization. Description Modern and refined, this solitaire ring features an emerald-cut lab diamond set in a smooth bezel setting with a distinctive east-west orientation , placing the stone horizontally for a fresh, contemporary look. The step-cut facets offer a calm, mirror-like brilliance, while the bezel provides a sleek, secure frame that enhances the clean… | F68: 18K Gold | G68: Lab Grown Diamond | H68: 2 | I68: 2 ct | J68: 2ct Emerald Cut Lab Diamond DEF VS | K68: 2106.75 | L68: =K68*(1-Pricing!$B$4) | M68: =L68*Pricing!$B$9*(1+Pricing!$B$6+Pricing!$B$7)+Pricing!$B$5 | N68: =M68*(1+Pricing!$B$8) | O68: =N68-M68 | P68: View Product | Q68: Fiorese Jewelry | R68: Open Image | S68: 1
A69: 66 | C69: Old Mine-Cut Lab Diamond Engagement Ring with Vintage Setting | D69: Engagement Ring | E69: Stone Type: Lab Diamond Center Stone: custom 1.5ct old mine cut FG VS Band Width: 2mm Band Thickness: 1.8mm If you have any special requests for this design (such as metal, gemstone, or design details), please contact our advisor for customization. Description Distinctive and richly detailed, this Old Mine-cut lab diamond solitaire engagement ring features a refined double-prong basket setting that adds both visual intricacy and secure support to the center stone. The paired prongs delicately frame each corner, subtly emphasizing the diamond’s soft, antique proportions while allowing light… | F69: 18K Gold | G69: Lab Grown Diamond | H69: 1.5 | I69: 1.5 ct | J69: 1.5ct old mine cut FG VS | K69: 2115.75 | L69: =K69*(1-Pricing!$B$4) | M69: =L69*Pricing!$B$9*(1+Pricing!$B$6+Pricing!$B$7)+Pricing!$B$5 | N69: =M69*(1+Pricing!$B$8) | O69: =N69-M69 | P69: View Product | Q69: Fiorese Jewelry | R69: Open Image | S69: 1
A70: 67 | C70: Round-Cut Lab Diamond Channel Half Eternity Ring | D70: Engagement Ring | E70: Stone Type: Lab Diamond Stone Spec: 2.5mm round cut DEF VS If you have any special requests for this design (such as metal, gemstone, or design details), please contact our advisor for customization. Description Elegant, refined, and timelessly sophisticated, this half eternity ring features a row of luminous round-cut lab diamonds secured within a sleek channel setting , crafted in luxurious 18K white gold for a polished and contemporary finish. The classic round diamonds radiate exceptional brilliance, creating a seamless ribbon of light across the finger with understated luxury appeal.… | F70: 18K Gold | G70: Lab Grown Diamond | I70: 2.5mm (per stone) | J70: 2.5mm Round cut DEF VS | K70: 2116.5 | L70: =K70*(1-Pricing!$B$4) | M70: =L70*Pricing!$B$9*(1+Pricing!$B$6+Pricing!$B$7)+Pricing!$B$5 | N70: =M70*(1+Pricing!$B$8) | O70: =N70-M70 | P70: View Product | Q70: Fiorese Jewelry | R70: Open Image | S70: 1
A71: 68 | C71: Brown Round-Cut Lab Diamond Solitaire Ring with Cathedral Setting | D71: Engagement Ring | E71: Stone Type: Lab Diamond Center Stone: custom 0.6ct round cut brown VS about 5.4mm Band Width: 2.2mm Band Thickness: 1.8mm If you have any special requests for this design (such as metal, gemstone, or design details), please contact our advisor for customization. Description Rich in character and vintage artistry, this brown round-cut lab diamond solitaire engagement ring pairs a refined 4-claw cathedral setting with a beautifully floral engraved band , creating a design that feels both romantic and timeless. The cathedral shoulders rise gracefully to elevate the center stone, enhancing its… | F71: 18K Gold | G71: Lab Grown Diamond | H71: 0.6 | I71: 0.6 ct | J71: 0.6ct Round Cut Lab Diamond Brown VS | K71: 2124.75 | L71: =K71*(1-Pricing!$B$4) | M71: =L71*Pricing!$B$9*(1+Pricing!$B$6+Pricing!$B$7)+Pricing!$B$5 | N71: =M71*(1+Pricing!$B$8) | O71: =N71-M71 | P71: View Product | Q71: Fiorese Jewelry | R71: Open Image | S71: 1
A72: 69 | C72: Round Yellow Lab Diamond Celestial-Inspired Ring with Sun, Moon and Star Motifs | D72: Engagement Ring | E72: Stone Type: Lab Diamond Center Stone: 1ct round cut yellow VS-SI Side Stone: round cut DEF VS Band Width: 2mm Band Thickness: 1.8mm If you have any special requests for this design (such as metal, gemstone, or design details), please contact our advisor for customization. Description Radiant and symbolic, this celestial-inspired ring features a glowing round yellow lab diamond at its center, representing the warmth of the sun. Surrounding it, delicate sun, new moon, and star motifs create a poetic cosmic narrative, celebrating cycles of light, renewal, and guidance. Perfect for those drawn… | F72: 18K Gold | G72: Lab Grown Diamond | H72: 1 | I72: 1 ct | J72: 1ct Yellow Round Lab Diamond VS-SI | K72: 2126.25 | L72: =K72*(1-Pricing!$B$4) | M72: =L72*Pricing!$B$9*(1+Pricing!$B$6+Pricing!$B$7)+Pricing!$B$5 | N72: =M72*(1+Pricing!$B$8) | O72: =N72-M72 | P72: View Product | Q72: Fiorese Jewelry | R72: Open Image | S72: 1
A73: 70 | C73: Round-Cut Lab Diamond Eternity Ring with Micropavé | D73: Engagement Ring | E73: Stone Type: Lab Diamond Stone Spec: 1.2mm round cut DEF VS Band Width: 3mm Band Thickness: 2mm If you have any special requests for this design (such as metal, gemstone, or design details), please contact our advisor for customization. Description Delicate, radiant, and timelessly refined, this micropavé eternity ring features a continuous circle of shimmering round-cut lab diamonds meticulously set to create an uninterrupted surface of brilliance. The fine micropavé craftsmanship enhances the ring with an ultra-luminous sparkle and elegant, refined texture. Each diamond is carefully… | F73: 18K Gold | G73: Lab Grown Diamond | I73: 1.2mm (per stone) | J73: 1.2mm round cut DEF VS | K73: 2141.25 | L73: =K73*(1-Pricing!$B$4) | M73: =L73*Pricing!$B$9*(1+Pricing!$B$6+Pricing!$B$7)+Pricing!$B$5 | N73: =M73*(1+Pricing!$B$8) | O73: =N73-M73 | P73: View Product | Q73: Fiorese Jewelry | R73: Open Image | S73: 1
A74: 71 | C74: Old European-Cut Lab Diamond Three-Stone Ring with Tulip Setting | D74: Engagement Ring | E74: Stone: custom 1.5ct old European cut lab diamond FG VS Side Stone: 1.5mm round cut lab diamond DEF VS Band Width: 2mm Band Thickness: 1.8mm If you have any special requests for this design (such as metal, gemstone, or design details), please contact our advisor for customization. Description Romantic, heirloom-inspired, and elegantly refined, this three-stone engagement ring features a luminous old European-cut lab diamond accented by sparkling round lab diamond side stones , creating a timeless composition rich in antique character and symbolic beauty. The old European cut is celebrated for… | F74: 18K White Gold | G74: Lab Grown Diamond | H74: 1.5 | I74: 1.5 ct | J74: 1.5ct old European cut Lab Diamond FG VS | K74: 2159.25 | L74: =K74*(1-Pricing!$B$4) | M74: =L74*Pricing!$B$9*(1+Pricing!$B$6+Pricing!$B$7)+Pricing!$B$5 | N74: =M74*(1+Pricing!$B$8) | O74: =N74-M74 | P74: View Product | Q74: Fiorese Jewelry | R74: Open Image | S74: 3
A75: 72 | C75: Old European-Cut & Emerald-Cut Lab Diamond Toi et Moi Ring | D75: Engagement Ring | E75: Stone 1: 1ct emerald cut lab diamond DEF VS Stone 2: custom 0.25ct old European cut lab diamond DEF VS Band Width: 2.2mm Band Thickness: 1.8mm If you have any special requests for this design (such as metal, gemstone, or design details), please contact our advisor for customization. Description Distinctive, romantic, and artistically refined, this Toi et Moi engagement ring features a captivating pairing of an old European-cut lab diamond and an emerald-cut lab diamond , symbolizing two contrasting yet perfectly connected souls. The combination of soft antique brilliance and sleek step-cut… | F75: 18K Gold | G75: Lab Grown Diamond | H75: 1 | I75: 1 ct | J75: 1ct emerald cut lab diamonds DEF VS | K75: 2176.5 | L75: =K75*(1-Pricing!$B$4) | M75: =L75*Pricing!$B$9*(1+Pricing!$B$6+Pricing!$B$7)+Pricing!$B$5 | N75: =M75*(1+Pricing!$B$8) | O75: =N75-M75 | P75: View Product | Q75: Fiorese Jewelry | R75: Open Image | S75: 1
A76: 73 | C76: Princess-Cut Lab Diamond Eternity Band with U-Shaped Prong Setting | D76: Engagement Ring | E76: Stone Spec: 3.5*3.5mm princess cut lab diamond DEF VS If you have any special requests for this design (such as metal, gemstone, or design details), please contact our advisor for customization. Description Bold, refined, and endlessly radiant, this eternity band features a continuous circle of shimmering princess-cut lab diamonds secured in a sleek shared prong setting . The clean geometric lines and sharp symmetry of the princess cuts create striking brilliance with a distinctly modern sophistication. Crafted with a graceful U-shaped base , the setting allows maximum light exposure beneath… | F76: 18K Gold | G76: Lab Grown Diamond | I76: 3.5×3.5mm (per stone) | J76: 3.5*3.5mm Princess Cut DEF VS | K76: 2179.5 | L76: =K76*(1-Pricing!$B$4) | M76: =L76*Pricing!$B$9*(1+Pricing!$B$6+Pricing!$B$7)+Pricing!$B$5 | N76: =M76*(1+Pricing!$B$8) | O76: =N76-M76 | P76: View Product | Q76: Fiorese Jewelry | R76: Open Image | S76: 1
A77: 74 | C77: Round Brilliant-Cut Lab Diamond Ring with Bean-Shaped Pavé Head | D77: Engagement Ring | E77: Stone Type: Lab Diamond Pave: round cut DEF VS Bean's Size: 11.5*8mm Band Width: 1.6mm Band Thickness: 1.6mm If you have any special requests for this design (such as metal, gemstone, or design details), please contact our advisor for customization. Description Graceful and organic, this ring features a luminous round brilliant-cut lab diamond set within a distinctive bean-shaped head , creating a soft, flowing silhouette inspired by natural forms. The pavé setting adds a delicate layer of continuous sparkle, enhancing the ring’s brilliance while maintaining a refined, elegant profile.… | F77: 18K Gold | G77: Lab Grown Diamond | I77: 11.5×8mm (per stone) | J77: Round cut lab diamond DEF VVS-VS | K77: 2186.25 | L77: =K77*(1-Pricing!$B$4) | M77: =L77*Pricing!$B$9*(1+Pricing!$B$6+Pricing!$B$7)+Pricing!$B$5 | N77: =M77*(1+Pricing!$B$8) | O77: =N77-M77 | P77: View Product | Q77: Fiorese Jewelry | R77: Open Image | S77: 1
A78: 75 | C78: Round-Cut Lab Diamond Three-Stone Ring with Cathedral Setting | D78: Engagement Ring | E78: Stone: 1.5ct round cut lab diamond DEF VS Side Stone: pear cut lab diamond DEF VS about 0.42 ct tw Band Width: 2mm Band Thickness: 1.8mm If you have any special requests for this design (such as metal, gemstone, or design details), please contact our advisor for customization. Description Elegant, timeless, and beautifully balanced, this three-stone engagement ring features a radiant round-cut lab diamond accented by graceful pear-shaped side stones , symbolizing the past, present, and future through a refined composition of brilliance and harmony. The classic round center stone delivers… | F78: 18K Gold | G78: Lab Grown Diamond | H78: 1.5 | I78: 1.5 ct | J78: 1.5ct Round Cut Lab Diamond DEF VS | K78: 2190 | L78: =K78*(1-Pricing!$B$4) | M78: =L78*Pricing!$B$9*(1+Pricing!$B$6+Pricing!$B$7)+Pricing!$B$5 | N78: =M78*(1+Pricing!$B$8) | O78: =N78-M78 | P78: View Product | Q78: Fiorese Jewelry | R78: Open Image | S78: 1
A79: 76 | C79: Oval-Cut Lab Diamond Solitaire Ring with Martini Setting | D79: Engagement Ring | E79: Stone Type: Lab Diamond Center Stone: 2ct oval cut DEF VS Band Width: 1.7mm Band Thickness: 1.7mm If you have any special requests for this design (such as metal, gemstone, or design details), please contact our advisor for customization. Description Sleek and understated, this oval-cut lab diamond solitaire ring features a refined 4-prong martini setting designed to sit low on the finger for a comfortable, streamlined wear. The martini-style base tapers neatly beneath the center stone, allowing the diamond to appear as if it is gently floating, while maintaining a secure and balanced hold.… | F79: 18K Gold | G79: Lab Grown Diamond | H79: 2 | I79: 2 ct | J79: 2ct oval cut DEF VS | K79: 2199 | L79: =K79*(1-Pricing!$B$4) | M79: =L79*Pricing!$B$9*(1+Pricing!$B$6+Pricing!$B$7)+Pricing!$B$5 | N79: =M79*(1+Pricing!$B$8) | O79: =N79-M79 | P79: View Product | Q79: Fiorese Jewelry | R79: Open Image | S79: 1
A80: 77 | C80: Heart-Cut Pink Lab Diamond Bezel Solitaire Ring with Tapered Band | D80: Engagement Ring | E80: Stone Type: Lab Diamond Center Stone: 1ct heart cut pink VS Band Width: 2.2mm Band Thickness: 1.5mm If you have any special requests for this design (such as metal, gemstone, or design details), please contact our advisor for customization. Description Romantic and refined, this solitaire ring features a heart-cut pink lab diamond framed in a smooth bezel setting , highlighting its soft blush tone with a clean, modern edge. The tapered band enhances the overall balance, gently drawing attention to the center stone while maintaining a graceful silhouette. Perfect for those who appreciate… | F80: 18K Gold | G80: Lab Grown Diamond | H80: 1 | I80: 1 ct | J80: 1ct heart cut PInk VS | K80: 2215.5 | L80: =K80*(1-Pricing!$B$4) | M80: =L80*Pricing!$B$9*(1+Pricing!$B$6+Pricing!$B$7)+Pricing!$B$5 | N80: =M80*(1+Pricing!$B$8) | O80: =N80-M80 | P80: View Product | Q80: Fiorese Jewelry | R80: Open Image | S80: 1
A81: 78 | C81: Oval-Cut Lab Diamond Solitaire Ring with Martini Setting | D81: Engagement Ring | E81: Stone Type: Lab Diamond Center Stone: 1.5ct oval cut DEF VS Band Width: 2mm Band Thickness: 2mm If you have any special requests for this design (such as metal, gemstone, or design details), please contact our advisor for customization. Description Sculptural and contemporary, this oval-cut lab diamond solitaire ring pairs a sleek 4-prong martini setting with a distinctive bombé shank , creating a design that feels both fluid and architectural. The martini setting allows the diamond to sit low and close to the finger, offering a comfortable, streamlined profile while keeping the focus… | F81: 18K Gold | G81: Lab Grown Diamond | H81: 1.5 | I81: 1.5 ct | J81: 1.5ct oval cut DEF VS | K81: 2232.75 | L81: =K81*(1-Pricing!$B$4) | M81: =L81*Pricing!$B$9*(1+Pricing!$B$6+Pricing!$B$7)+Pricing!$B$5 | N81: =M81*(1+Pricing!$B$8) | O81: =N81-M81 | P81: View Product | Q81: Fiorese Jewelry | R81: Open Image | S81: 1
A82: 79 | C82: Round Lab Diamond Eternity Ring with Shared Prong Basket | D82: Engagement Ring | E82: Stone Type: Lab Diamond Stone Spec: 4.3mm round cut DEF VS If you have any special requests for this design (such as metal, gemstone, or design details), please contact our advisor for customization. Description Bold, radiant, and timelessly refined, this eternity ring features a continuous circle of luminous 4.3mm round lab diamonds secured in elegant shared prong basket settings . The classic round cuts maximize fire and brilliance, creating an uninterrupted ribbon of dazzling sparkle around the finger. The shared prong design minimizes visible metal, allowing the diamonds to sit closely… | F82: 18K Gold | G82: Lab Grown Diamond | I82: 4.3mm (per stone) | J82: 4.3mm Round cut DEF VS | K82: 2247 | L82: =K82*(1-Pricing!$B$4) | M82: =L82*Pricing!$B$9*(1+Pricing!$B$6+Pricing!$B$7)+Pricing!$B$5 | N82: =M82*(1+Pricing!$B$8) | O82: =N82-M82 | P82: View Product | Q82: Fiorese Jewelry | R82: Open Image | S82: 1
A83: 80 | C83: Oval Lab Diamond Ring with Basket Setting and Mixed-Cut Side Stones | D83: Engagement Ring | E83: Stone Type: Lab Diamond Center Stone: 1.5ct oval cut DEF VS Side Stone: round and pear cut DEF VS Band Width: 1.8mm Band Thickness: 1.8mm If you have any special requests for this design (such as metal, gemstone, or design details), please contact our advisor for customization. Description Elegant and luminous, this ring features a 1.5ct oval lab diamond secured in a classic four-claw prong basket setting , allowing light to enhance its brilliance from every angle. The elongated shape offers a graceful, finger-flattering silhouette. Accentuating the center stone, round and pear-cut lab… | F83: 18K Gold | G83: Lab Grown Diamond | H83: 1.5 | I83: 1.5 ct | J83: 1.5ct oval cut DEF VS | K83: 2255.25 | L83: =K83*(1-Pricing!$B$4) | M83: =L83*Pricing!$B$9*(1+Pricing!$B$6+Pricing!$B$7)+Pricing!$B$5 | N83: =M83*(1+Pricing!$B$8) | O83: =N83-M83 | P83: View Product | Q83: Fiorese Jewelry | R83: Open Image | S83: 1
A84: 81 | C84: Round Brilliant-Cut Lab Diamond Three-Stone Ring with Cathedral Setting | D84: Engagement Ring | E84: Stone: 1ct round cut lab diamond DEF VS Side Stone 1: 0.5ct round cut lab diamond DEF VS about 1 ct tw Side Stone 2: round cut lab diamond DEF VS ( half pave) Band Width: 2.5mm Band Thickness: 1.5mm If you have any special requests for this design (such as metal, gemstone, or design details), please contact our advisor for customization. Description Elegant, timeless, and richly radiant, this three-stone ring features a luminous arrangement of round brilliant-cut lab diamonds , symbolizing the past, present, and future through a refined composition of exceptional sparkle and balance. The… | F84: 18K Gold | G84: Lab Grown Diamond | H84: 1 | I84: 1 ct | J84: 1ct Round Brilliant Cut Lab Diamond DEF VS | K84: 2261.25 | L84: =K84*(1-Pricing!$B$4) | M84: =L84*Pricing!$B$9*(1+Pricing!$B$6+Pricing!$B$7)+Pricing!$B$5 | N84: =M84*(1+Pricing!$B$8) | O84: =N84-M84 | P84: View Product | Q84: Fiorese Jewelry | R84: Open Image | S84: 1
A85: 82 | C85: Asscher-Cut Lab Diamond Bezel 2/3 Eternity Ring with Two-Tone Design | D85: Engagement Ring | E85: Stone Type: Lab Diamond Stone Spec: 3.5*3.5mm asscher cut DEF VS (2/3 eternity) Band Width: 2mm Band Thickness: 1.8mm If you have any special requests for this design (such as metal, gemstone, or design details), please contact our advisor for customization. Description Architectural, refined, and timelessly elegant, this 2/3 eternity ring features a graceful row of 3.5×3.5mm Asscher-cut lab diamonds framed within sleek bezel settings , crafted in 14K gold with rhodium-plated two-tone detailing . Inspired by the geometric glamour of the Art Deco era, the design celebrates clean lines,… | F85: 18K Gold | G85: Lab Grown Diamond | I85: 3.5×3.5mm (per stone) | J85: 3.5*3.5mm Asscher Cut DEF VS | K85: 2263.5 | L85: =K85*(1-Pricing!$B$4) | M85: =L85*Pricing!$B$9*(1+Pricing!$B$6+Pricing!$B$7)+Pricing!$B$5 | N85: =M85*(1+Pricing!$B$8) | O85: =N85-M85 | P85: View Product | Q85: Fiorese Jewelry | R85: Open Image | S85: 1
A86: 83 | C86: Radiant-Cut Lab Diamond Three-Stone Ring with Triangular Side Stones | D86: Engagement Ring | E86: Stone: 1.5ct radiant cut lab diamond DEF VS Side Stone: triangle cut lab diamond DEF VS about 0.28 ct tw Band Width: 2mm Band Thickness: 1.8mm If you have any special requests for this design (such as metal, gemstone, or design details), please contact our advisor for customization. Description Bold, radiant, and architecturally refined, this three-stone engagement ring features a dazzling radiant-cut lab diamond accented by striking triangular-cut lab diamond side stones , creating a sophisticated composition filled with brilliance, symmetry, and modern elegance. The radiant cut combines… | F86: 18K Gold | G86: Lab Grown Diamond | H86: 1.5 | I86: 1.5 ct | J86: 1.5ct Radiant cut DEF VS | K86: 2297.25 | L86: =K86*(1-Pricing!$B$4) | M86: =L86*Pricing!$B$9*(1+Pricing!$B$6+Pricing!$B$7)+Pricing!$B$5 | N86: =M86*(1+Pricing!$B$8) | O86: =N86-M86 | P86: View Product | Q86: Fiorese Jewelry | R86: Open Image | S86: 1
A87: 84 | C87: Oval Lab Diamond Vintage Ring with Millegrain Detailing and Halo | D87: Engagement Ring | E87: Stone Type: Lab Diamond Center Stone:7*5mm oval cut DEF VS Side Stone: round and tapered baguette cut DEF VS Band Width: 2mm Band Thickness: 1.8mm If you have any special requests for this design (such as metal, gemstone, or design details), please contact our advisor for customization. Description Elegant and richly detailed, this vintage-style ring features a luminous oval lab diamond framed by a delicate halo setting that enhances its brilliance and presence. Intricate millegrain detailing adds antique texture and craftsmanship, giving the design a true heirloom character. Flanking the… | F87: 18K Gold | G87: Lab Grown Diamond | I87: 7×5mm (per stone) | J87: 7*5mm Oval Cut Lab Diamond DEF VVS-VS | K87: 2298 | L87: =K87*(1-Pricing!$B$4) | M87: =L87*Pricing!$B$9*(1+Pricing!$B$6+Pricing!$B$7)+Pricing!$B$5 | N87: =M87*(1+Pricing!$B$8) | O87: =N87-M87 | P87: View Product | Q87: Fiorese Jewelry | R87: Open Image | S87: 1
A88: 85 | C88: Oval-Cut Lab Diamond Half Eternity Ring with Shared Prong Setting | D88: Engagement Ring | E88: Stone Type: Lab Diamond Stone Spec: 6*4mm oval cut DEF VS Band Width: 2.2mm Band Thickness: 1.6mm If you have any special requests for this design (such as metal, gemstone, or design details), please contact our advisor for customization. Description Elegant, radiant, and timelessly refined, this half eternity ring features a graceful row of luminous 6×4mm oval-cut lab diamonds secured in a delicate U-shaped basket shared prong setting , crafted in rich 14K yellow gold for a warm and sophisticated finish. The elongated oval silhouettes create soft fluid brilliance while enhancing the finger… | F88: 18K Gold | G88: Lab Grown Diamond | I88: 6×4mm (per stone) | J88: 6*4mm Oval Cut Lab Diamond DEF VS | K88: 2308.5 | L88: =K88*(1-Pricing!$B$4) | M88: =L88*Pricing!$B$9*(1+Pricing!$B$6+Pricing!$B$7)+Pricing!$B$5 | N88: =M88*(1+Pricing!$B$8) | O88: =N88-M88 | P88: View Product | Q88: Fiorese Jewelry | R88: Open Image | S88: 2
A89: 86 | C89: Rose-Cut Lab Diamond Bezel Solitaire Ring | D89: Engagement Ring | E89: Stone Type: Lab Diamond Center Stone: custom 1.5ct rose cut FG VS Band Width: 2mm Band Thicknes: 1.8mm If you have any special requests for this design (such as metal, gemstone, or design details), please contact our advisor for customization. Description Delicate, romantic, and effortlessly timeless, this solitaire ring features a captivating 1.5ct rose-cut lab diamond framed within a refined bezel setting , crafted in luminous 14K white gold . Inspired by centuries-old diamond-cutting traditions, the design celebrates understated elegance, soft reflections, and heirloom-worthy… | F89: 18K Gold | G89: Lab Grown Diamond | H89: 1.5 | I89: 1.5 ct | J89: 1.5ct Rose Cut Lab Diamond FG VS | K89: 2331.75 | L89: =K89*(1-Pricing!$B$4) | M89: =L89*Pricing!$B$9*(1+Pricing!$B$6+Pricing!$B$7)+Pricing!$B$5 | N89: =M89*(1+Pricing!$B$8) | O89: =N89-M89 | P89: View Product | Q89: Fiorese Jewelry | R89: Open Image | S89: 1
A90: 87 | C90: Rose-Cut Lab Diamond Bezel Solitaire Ring with Tapered Band | D90: Engagement Ring | E90: Stone Type: Lab Diamond Center Stone: custom 1.5ct rose cut FG VS Band Width: 2mm Band Thickness: 1.8mm If you have any special requests for this design (such as metal, gemstone, or design details), please contact our advisor for customization. Description Soft and luminous, this ring features a rose-cut lab diamond set in a smooth bezel setting , highlighting its subtle, diffused sparkle and antique charm. The tapered band enhances the overall balance, gently drawing the eye toward the center stone while maintaining a clean, elegant silhouette. Perfect for those who appreciate… | F90: 18K Gold | G90: Lab Grown Diamond | H90: 1.5 | I90: 1.5 ct | J90: 1.5ct Rose Cut Lab Diamond FG VS | K90: 2331.75 | L90: =K90*(1-Pricing!$B$4) | M90: =L90*Pricing!$B$9*(1+Pricing!$B$6+Pricing!$B$7)+Pricing!$B$5 | N90: =M90*(1+Pricing!$B$8) | O90: =N90-M90 | P90: View Product | Q90: Fiorese Jewelry | R90: Open Image | S90: 1
A91: 88 | C91: Old Mine-Cut Lab-Grown Diamond Vintage Ring with Floral Basket Setting | D91: Engagement Ring | E91: Stone Type: Lab Diamond Center Stone: custom 1.5ct old mine cut FG VS Side Stone: round cut DEF VS Band Width: 2mm Band Thickness: 1.8mm If you have any special requests for this design (such as metal, gemstone, or design details), please contact our advisor for customization. Description Romantic and intricately crafted, this vintage-inspired ring features an Old Mine-cut lab-grown diamond secured in a graceful triple-prong floral basket setting , echoing the soft curves of blooming petals. The design draws from Art Nouveau nature-inspired aesthetics , with flowing lines and organic… | F91: 18K Gold | G91: Lab Grown Diamond | H91: 1.5 | I91: 1.5 ct | J91: 1.5ct old mine cut FG VS | K91: 2334 | L91: =K91*(1-Pricing!$B$4) | M91: =L91*Pricing!$B$9*(1+Pricing!$B$6+Pricing!$B$7)+Pricing!$B$5 | N91: =M91*(1+Pricing!$B$8) | O91: =N91-M91 | P91: View Product | Q91: Fiorese Jewelry | R91: Open Image | S91: 1
A92: 89 | C92: Cushion-Cut Lab Diamond Eternity Ring with U-Shaped Prong Setting | D92: Engagement Ring | E92: Stone Spec: 4*4mm cushion cut lab diamond DEF VS If you have any special requests for this design (such as metal, gemstone, or design details), please contact our advisor for customization. Description Elegant, radiant, and endlessly timeless, this eternity ring features a continuous circle of luminous cushion-cut lab diamonds secured in a refined shared prong setting . The softly rounded cushion silhouettes create a romantic balance of brilliance and gentle geometry, offering exceptional sparkle with sophisticated dimension. Designed with a graceful U-shaped base , the setting allows… | F92: 18K Gold | G92: Lab Grown Diamond | I92: 4×4mm (per stone) | J92: 4*4mm Cushion Cut DEF VS | K92: 2336.25 | L92: =K92*(1-Pricing!$B$4) | M92: =L92*Pricing!$B$9*(1+Pricing!$B$6+Pricing!$B$7)+Pricing!$B$5 | N92: =M92*(1+Pricing!$B$8) | O92: =N92-M92 | P92: View Product | Q92: Fiorese Jewelry | R92: Open Image | S92: 1
A93: 90 | C93: Marquise-Cut Lab Diamond Solitaire Ring with Six-Claw Setting | D93: Engagement Ring | E93: Stone Type: Lab Diamond Center Stone: 1.5ct marquise cut DEF VS Band Width: 2.2mm Band Thickness: 1.8mm If you have any special requests for this design (such as metal, gemstone, or design details), please contact our advisor for customization. Description Inspired by the fluid beauty of nature, this marquise-cut lab diamond solitaire ring features a refined six-claw setting presented within an Art Nouveau–inspired, nature-themed design . The elongated marquise shape is elegantly framed by the evenly spaced prongs, which secure the stone while accentuating its pointed ends and graceful,… | F93: 18K Gold | G93: Lab Grown Diamond | H93: 1.5 | I93: 1.5 ct | J93: 1.5ct marquise cut DEF VS | K93: 2361.75 | L93: =K93*(1-Pricing!$B$4) | M93: =L93*Pricing!$B$9*(1+Pricing!$B$6+Pricing!$B$7)+Pricing!$B$5 | N93: =M93*(1+Pricing!$B$8) | O93: =N93-M93 | P93: View Product | Q93: Fiorese Jewelry | R93: Open Image | S93: 1
A94: 91 | C94: Old European-Cut Lab Diamond Three-Stone Engagement Ring with Cathedral Setting, Tapered Band and Half Pavé | D94: Engagement Ring | E94: Description Vintage-inspired and elegant, this Old European-cut lab diamond three-stone engagement ring features a graceful cathedral setting , tapered band , and half pavé diamond accents . The antique-style brilliance and refined detailing symbolize past, present, and future with timeless heirloom charm. Metal 14K Gold Stone Lab Diamond Center Stones 1ct old european cut lab diamond FG VS, 6.5*6.5mm Customization is required Side-stone 1 2 pieces of round lab diamond DEF VS, 5*5mm, 1 ct tw Side-stone 2 Round lab diamond DEF VS, from 1.7 to 1 mm ( Half Pavé ) Band Width 2.5mm Band Thickness… | F94: 18K Gold | G94: Lab Grown Diamond | H94: 1 | I94: 1 ct | J94: 1ct Old European Cut Lab Diamond FG VS | K94: 2403.75 | L94: =K94*(1-Pricing!$B$4) | M94: =L94*Pricing!$B$9*(1+Pricing!$B$6+Pricing!$B$7)+Pricing!$B$5 | N94: =M94*(1+Pricing!$B$8) | O94: =N94-M94 | P94: View Product | Q94: Fiorese Jewelry | R94: Open Image | S94: 1
A95: 92 | C95: Princess-Cut Lab Diamond Solitaire Ring with Martini Setting | D95: Engagement Ring | E95: Stone Type: Lab Diamond Center Stone: 2ct princess cut DEF VS Band Width: 2mm Band Thickness: 1.8mm If you have any special requests for this design (such as metal, gemstone, or design details), please contact our advisor for customization. Description Clean-lined and distinctly modern, this princess-cut lab diamond solitaire ring features a streamlined 4-prong martini setting that allows the stone to sit low and close to the finger for a comfortable, understated profile. The martini-style base tapers beneath the diamond, creating the appearance of a subtle floating effect while maintaining… | F95: 18K Gold | G95: Lab Grown Diamond | H95: 2 | I95: 2 ct | J95: 2ct princess cut DEF VS | K95: 2454 | L95: =K95*(1-Pricing!$B$4) | M95: =L95*Pricing!$B$9*(1+Pricing!$B$6+Pricing!$B$7)+Pricing!$B$5 | N95: =M95*(1+Pricing!$B$8) | O95: =N95-M95 | P95: View Product | Q95: Fiorese Jewelry | R95: Open Image | S95: 1
A96: 93 | C96: Pear-Cut Lab Diamond Cathedral Ring with Twisted Pavé Floral Basket | D96: Engagement Ring | E96: Stone Type: Lab Diamond Center Stone: 2ct pear cut DEF VS Side Stone: round cut DEF VS Band Width: 2mm Band Thickness: 2mm If you have any special requests for this design (such as metal, gemstone, or design details), please contact our advisor for customization. Description Romantic and delicately sculpted, this ring features a luminous 2ct pear-cut lab diamond elevated in a graceful cathedral setting , enhancing its brilliance and elegant teardrop silhouette. The floral basket setting beneath the center stone adds intricate, nature-inspired detail, while the twisted pavé band brings… | F96: 18K Gold | G96: Lab Grown Diamond | H96: 2 | I96: 2 ct | J96: 2ct Pear Cut Lab Diamond DEF VS | K96: 2461.5 | L96: =K96*(1-Pricing!$B$4) | M96: =L96*Pricing!$B$9*(1+Pricing!$B$6+Pricing!$B$7)+Pricing!$B$5 | N96: =M96*(1+Pricing!$B$8) | O96: =N96-M96 | P96: View Product | Q96: Fiorese Jewelry | R96: Open Image | S96: 1
A97: 94 | C97: Cushion Rose-Cut Lab Diamond Three-Stone Ring with Millegrain Bezel Setting | D97: Engagement Ring | E97: Stone: custom 1.5ct cushion rose cut lab diamond FG VS Side Stone: pear cut lab diamond DEF VS about 0.2 ct tw Band Width: 2mm Band Thickness: 1.8mm If you have any special requests for this design (such as metal, gemstone, or design details), please contact our advisor for customization. Description Romantic, ethereal, and richly heirloom-inspired, this three-stone engagement ring features a luminous cushion rose-cut lab diamond accented by graceful pear-shaped side stones , creating a poetic composition filled with antique charm and timeless sophistication. The rose-cut diamond reveals… | F97: 18K Gold | G97: Lab Grown Diamond | H97: 1.5 | I97: 1.5 ct | J97: 1.5ct cushion rose cut Lab Diamond FG VS | K97: 2470.5 | L97: =K97*(1-Pricing!$B$4) | M97: =L97*Pricing!$B$9*(1+Pricing!$B$6+Pricing!$B$7)+Pricing!$B$5 | N97: =M97*(1+Pricing!$B$8) | O97: =N97-M97 | P97: View Product | Q97: Fiorese Jewelry | R97: Open Image | S97: 1
A98: 95 | C98: Old European-Cut Lab Diamond Three-Stone Ring with Cathedral Setting | D98: Engagement Ring | E98: Stone: custom 1ct old European cut lab diamond FG VS Side Stone: round cut lab diamond DEF VS about 1 ct tw Band Width: 2.5mm Band Thickness: 1.5mm If you have any special requests for this design (such as metal, gemstone, or design details), please contact our advisor for customization. Description Romantic, heirloom-inspired, and timelessly refined, this three-stone ring features luminous old European-cut lab diamonds arranged in a classic symbolic composition representing the past, present, and future. Celebrated for their broad antique facets and soft candlelit sparkle, the old European… | F98: 18K Gold | G98: Lab Grown Diamond | H98: 1 | I98: 1 ct | J98: 1ct Old European Cut Lab Diamond FG VS | K98: 2532.75 | L98: =K98*(1-Pricing!$B$4) | M98: =L98*Pricing!$B$9*(1+Pricing!$B$6+Pricing!$B$7)+Pricing!$B$5 | N98: =M98*(1+Pricing!$B$8) | O98: =N98-M98 | P98: View Product | Q98: Fiorese Jewelry | R98: Open Image | S98: 1
A99: 96 | C99: Old European-Cut Lab Diamond Matte Brushed Ring | D99: Engagement Ring | E99: Stone Type: Lab Diamond Pave: round cut DEF VS Band Width: 4mm Band Thickness: 2mm If you have any special requests for this design (such as metal, gemstone, or design details), please contact our advisor for customization. Description Understated yet refined, this ring features an Old European-cut lab diamond set against a matte brushed finish band , creating a beautiful contrast between soft vintage sparkle and contemporary texture. The antique-style facets of the diamond deliver a warm, romantic glow, while the brushed surface adds a modern, tactile elegance. Perfect for those who… | F99: 18K Gold | G99: Lab Grown Diamond | I99: 2.3mm (per stone) | J99: 14 pieces of 2.3mm old European cut DEF VS | K99: 2533.5 | L99: =K99*(1-Pricing!$B$4) | M99: =L99*Pricing!$B$9*(1+Pricing!$B$6+Pricing!$B$7)+Pricing!$B$5 | N99: =M99*(1+Pricing!$B$8) | O99: =N99-M99 | P99: View Product | Q99: Fiorese Jewelry | R99: Open Image | S99: 1
A100: 97 | C100: Round Lab Diamond Buckle-Inspired Ring | D100: Engagement Ring | E100: Stone Type: Lab Diamond Pave: round cut DEF VVS-VS Band Width: 2.3mm Band Thickness: 2.2mm If you have any special requests for this design (such as metal, gemstone, or design details), please contact our advisor for customization. Description Distinctive and symbolic, this ring features round lab diamonds integrated into a buckle-inspired design , representing connection, strength, and unity. The structured silhouette blends clean lines with subtle brilliance, creating a look that is both modern and meaningful. Perfect for those who appreciate unique design with refined detail , this ring… | F100: 18K Gold | G100: Lab Grown Diamond | I100: 2.3mm (per stone) | J100: Round lab diamond DEF VVS-VS | K100: 2533.5 | L100: =K100*(1-Pricing!$B$4) | M100: =L100*Pricing!$B$9*(1+Pricing!$B$6+Pricing!$B$7)+Pricing!$B$5 | N100: =M100*(1+Pricing!$B$8) | O100: =N100-M100 | P100: View Product | Q100: Fiorese Jewelry | R100: Open Image | S100: 1
A101: 98 | C101: Marquise-Cut Lab Diamond Ring with Tulip Basket and Pavé Split Band | D101: Engagement Ring | E101: Stone Type: Lab Diamond Center Stone: 1.5ct marquise cut DEF VS Side Stone: round cut DEF VS Band Width: 2.2mm Band Thickness: 2mm If you have any special requests for this design (such as metal, gemstone, or design details), please contact our advisor for customization. Description Elegant and sculptural, this ring features a striking marquise-cut lab diamond secured in a graceful six-claw tulip basket setting , inspired by blooming petals that gently cradle the stone. The cathedral design elevates the center, enhancing brilliance and presence from every angle. A split band adorned with… | F101: 18K Gold | G101: Lab Grown Diamond | H101: 1.5 | I101: 1.5 ct | J101: 1.5ct marquise cut DEF VS | K101: 2541 | L101: =K101*(1-Pricing!$B$4) | M101: =L101*Pricing!$B$9*(1+Pricing!$B$6+Pricing!$B$7)+Pricing!$B$5 | N101: =M101*(1+Pricing!$B$8) | O101: =N101-M101 | P101: View Product | Q101: Fiorese Jewelry | R101: Open Image | S101: 1
A102: 99 | C102: Pear-Cut Lab Diamond Ring with Tulip Basket and Hidden Diamond Accent | D102: Engagement Ring | E102: Stone Type: Lab Diamond Center Stone: 2ct pear cut FG VS Side Stone: round cut DEF VS Band Width: 2.2mm Band Thickness: 1.8mm If you have any special requests for this design (such as metal, gemstone, or design details), please contact our advisor for customization. Description Delicate and romantic, this ring features a graceful pear-cut lab diamond held in a refined six-claw tulip basket setting , inspired by soft blooming petals. Beneath the center, a hidden round lab diamond adds a subtle, intimate sparkle known only to the wearer. The band is adorned with millegrain pavé detailing ,… | F102: 18K Gold | G102: Lab Grown Diamond | H102: 2 | I102: 2 ct | J102: 2ct Pear Cut Lab Diamond DEF VS | K102: 2544 | L102: =K102*(1-Pricing!$B$4) | M102: =L102*Pricing!$B$9*(1+Pricing!$B$6+Pricing!$B$7)+Pricing!$B$5 | N102: =M102*(1+Pricing!$B$8) | O102: =N102-M102 | P102: View Product | Q102: Fiorese Jewelry | R102: Open Image | S102: 1
A103: 100 | C103: Cushion-Cut Lab Diamond Eternity Ring with Shared Round Prong and Round Pavé | D103: Engagement Ring | E103: Stone Spec: 4.4mm cushion cut lab diamond DEF VS If you have any special requests for this design (such as metal, gemstone, or design details), please contact our advisor for customization. Description Radiant, luxurious, and beautifully detailed, this eternity ring features a continuous row of 4×4mm cushion-cut lab diamonds secured with delicate shared round prongs , crafted in luminous 14K white gold . The cushion-cut diamonds combine soft, romantic contours with exceptional brilliance, creating an elegant ribbon of sparkle that encircles the finger with timeless sophistication. Enhancing… | F103: 18K Gold | G103: Lab Grown Diamond | I103: 4×4mm (per stone) | J103: 4*4mm Cushion Cut DEF VS | K103: 2552.25 | L103: =K103*(1-Pricing!$B$4) | M103: =L103*Pricing!$B$9*(1+Pricing!$B$6+Pricing!$B$7)+Pricing!$B$5 | N103: =M103*(1+Pricing!$B$8) | O103: =N103-M103 | P103: View Product | Q103: Fiorese Jewelry | R103: Open Image | S103: 1
A104: 101 | C104: Cushion-Cut Lab Diamond Millegrain Bezel Solitaire Ring | D104: Engagement Ring | E104: Stone Type: Lab Diamond Center Stone: custom 1.5ct old mine cut FG VS Band Width: 2mm Band Thickness: 1.8mm If you have any special requests for this design (such as metal, gemstone, or design details), please contact our advisor for customization. Description Romantic and timeless, this solitaire ring features an Old Mine-cut lab diamond set in an antique-style millegrain bezel setting , enhancing its soft, candlelit brilliance. The delicate millegrain detailing adds texture and vintage charm, while the bezel design offers a smooth, secure frame that highlights the stone’s warm character.… | F104: 18K Gold | G104: Lab Grown Diamond | H104: 1.5 | I104: 1.5 ct | J104: 1.5ct old mine cut FG VS | K104: 2552.25 | L104: =K104*(1-Pricing!$B$4) | M104: =L104*Pricing!$B$9*(1+Pricing!$B$6+Pricing!$B$7)+Pricing!$B$5 | N104: =M104*(1+Pricing!$B$8) | O104: =N104-M104 | P104: View Product | Q104: Fiorese Jewelry | R104: Open Image | S104: 1
A105: 102 | C105: Cushion Brilliant-Cut Lab Diamond Eternity Ring with Shaped Claw Basket Setting | D105: Engagement Ring | E105: Stone Spec: 3.7*3.7mm cushion cut lab diamond DEF VS If you have any special requests for this design (such as metal, gemstone, or design details), please contact our advisor for customization. Description Elegant, radiant, and endlessly sophisticated, this eternity ring features a continuous row of cushion brilliant-cut lab diamonds secured in a refined shaped claw prong basket setting , crafted in luminous 14K white gold . The cushion-cut diamonds combine soft, romantic contours with exceptional brilliance, creating a seamless ribbon of sparkle that wraps beautifully around the finger.… | F105: 18K Gold | G105: Lab Grown Diamond | I105: 3.7×3.7mm (per stone) | J105: 3.7*3.7mm Cushion Cut DEF VS | K105: 2554.5 | L105: =K105*(1-Pricing!$B$4) | M105: =L105*Pricing!$B$9*(1+Pricing!$B$6+Pricing!$B$7)+Pricing!$B$5 | N105: =M105*(1+Pricing!$B$8) | O105: =N105-M105 | P105: View Product | Q105: Fiorese Jewelry | R105: Open Image | S105: 1
...

Sheet Pricing
A1: PRICING MODEL — edit the yellow cells only
A3: WHAT YOU PAY
A4: Wholesale discount off the listed price | B4: 0 | C4: THE MAIN LEVER. The listed prices are the sites’ RETAIL prices. Ask each supplier for their wholesale / OEM rate and enter it here (e.g. 40% means you pay 60% of the listed price). At 0% you are paying full retail and cannot price competitively.
A5: Shipping & insurance per piece (SAR) | B5: 0 | C5: A flat amount added to every piece.
A6: Customs, duty & VAT | B6: 0 | C6: Percentage added on the landed value.
A7: Payment / bank / platform fees | B7: 0 | C7: Card, transfer or marketplace fees.
A8: Profit margin | B8: 0.1 | C8: Your profit as a percentage ON TOP OF your landed cost (mark-up). 10% here = 9.1% of the selling price.
A9: USD → SAR exchange rate | B9: 3.75 | C9: Official Saudi riyal peg.
A12: HOW EACH PRICE IS BUILT
A13: 1. Your Cost (USD) | C13: Listed Price × (1 − wholesale discount)
A14: 2. Landed Cost (SAR) | C14: Your Cost × exchange rate × (1 + customs + fees) + shipping
A15: 3. FINAL PRICE (SAR) | C15: Landed Cost × (1 + profit margin)
A16: 4. Profit (SAR) | C16: Final Price − Landed Cost
A18: ⚠ The listed prices are RETAIL prices published on consumer websites, not wholesale. Selling at a 5–10% margin on top of full retail is not viable — the number you need is the wholesale discount in cell B4. All three suppliers run B2B / OEM programmes (Provence Gems is itself the manufacturer), and StarsGem prices by quotation only, which is why it carries no public prices at all.

Sheet Summary & Method
A1: LAB DIAMOND JEWELRY — EXTRACTION SUMMARY
A3: Markup multiplier (price + 110%) | B3: 2.1
A4: USD → SAR exchange rate | B4: 3.75
A5: Edit either yellow cell and every FINAL PRICE (SAR) recalculates.
A7: Unique items listed | B7: 1173
A8: Price range (USD) | B8: $119.00 – $109,251.00
A9: Average price | B9: $3,257.98
A10: Final price | B10: FINAL PRICE (SAR) = Price (USD) × 2.10 × 3.75 — cost + 110%, converted at the official Saudi riyal peg
A11: Final price range | B11: 937 – 860,352 SAR
A13: SOURCES
A14: Fiorese Jewelry | B14: 655 items · https://fioresejewelry.com/
A15: Provence Gems | B15: 306 items · https://provencegems.com/
A16: LGG Jewelry | B16: 212 items · https://www.lggjewelry.com/
A17: StarsGem (EXCLUDED) | B17: https://www.starsgem.com/ — removed: the site is quote-only and publishes no prices, so price and final-price columns could not be filled.
A19: BREAKDOWN BY METAL
A20: 18K Gold | B20: 1103 items
A21: 925 Silver | B21: 70 items
A23: BREAKDOWN BY CATEGORY
A24: Engagement Ring | B24: 312 items
A25: Stud Earrings | B25: 174 items
A26: Necklace | B26: 159 items
A27: Tennis Bracelet | B27: 129 items
A28: Ring | B28: 111 items
A29: Tennis Necklace | B29: 90 items
A30: Pendant | B30: 46 items
A31: Wedding/Eternity Band | B31: 43 items
A32: Bracelet | B32: 39 items
A33: Hoop Earrings | B33: 36 items
A34: Earrings | B34: 29 items
A35: Jewelry | B35: 5 items
A37: FILTERS & METHOD
A38: Metal filter | B38: Only solid 18K gold (white / yellow / rose) or 925 sterling silver. 10K, 14K, platinum and PT950 options were excluded.
A39: Stone filter | B39: Only jewelry whose MAIN / centre stone is a lab-grown diamond. Moissanite, cubic zirconia, lab sapphire / ruby / emerald / paraiba / padparadscha, moss agate and other gemstones were excluded, including pieces where a lab diamond appears only as a side stone.
A40: Scope | B40: Finished jewelry only — loose stones, melee and per-carat parcels excluded.
A41: Duplicate handling | B41: Items were grouped by design + metal + carat weight. Ring sizes, chain lengths and gold colours collapse into one row and the CHEAPEST qualifying option is the one listed. "Variants Merged" shows how many options were collapsed.
A42: 18K vs 925 | B42: Where a design is offered in both 18K gold and 925 silver, both appear as separate rows — they are different products at different prices, not duplicates.
A43: Weight | B43: "Weight (ct)" is the total lab-diamond carat weight taken from the product option or title. Blank where the seller does not state it. "Stone Size" gives the stone dimensions in mm where quoted instead.
A44: Price basis | B44: Lowest listed price of the qualifying option, in USD, as published at extraction time. Excludes shipping, duties and any customisation surcharge.
A45: Quote-only variants | B45: Variants priced as placeholders (e.g. "other carat weight", custom orders) were removed.
A46: Extracted | B46: 2026-09-04
