Workbook

Sheet All Photos
A1: LAB DIAMOND JEWELRY — 18K GOLD & 925 SILVER — FULL PHOTO GALLERY — Part 1 — Fiorese Jewelry
A2: Every photo published for each piece · Listed prices are the sites’ RETAIL prices · Set your wholesale discount, costs and profit % on the Pricing sheet · no links in this file
A3: # | B3: Product Name | C3: Description | D3: Weight | E3: Metal | F3: Listed Price (USD) | G3: Total Cost (SAR) | H3: FINAL PRICE (SAR) incl. VAT | I3: Net Profit (SAR) | J3: Discount needed | K3: Source | L3: Photos | M3: Photo 1 | N3: Photo 2 | O3: Photo 3 | P3: Photo 4 | Q3: Photo 5 | R3: Photo 6 | S3: Photo 7 | T3: Photo 8 | U3: Photo 9 | V3: Photo 10 | W3: Photo 11 | X3: Photo 12 | Y3: Photo 13 | Z3: Photo 14
A4: 1 | B4: Round Lab Diamond Pave Force Rope Chain Bracelet | C4: Stone Spec: Round Cut Lab Diamond DEF VS, 0.78 ct tw Please note, kindly specify your bracelet size in the remarks when placing the order. If you have any special requests for this design (such as metal, gemstone, or design details), please contact our advisor for customization. Description Bold and contemporary, this force rope chain bracelet features shimmering round lab diamonds in a refined pavé setting , combining the strength of classic chain styling with elevated fine jewelry… | D4: 0.78 ct | E4: 925 Sterling Silver | F4: 1063.2 | G4: =F4*(1-Pricing!$B$4)*Pricing!$B$3+(Pricing!$B$6+Pricing!$B$7+Pricing!$B$8+Pricing!$B$9+Pricing!$B$10+Pricing!$B$11+Pricing!$B$12+Pricing!$B$13) | H4: =G4/(1-Pricing!$B$15-Pricing!$B$16-Pricing!$B$17)*(1+Pricing!$B$18) | I4: =G4/(1-Pricing!$B$15-Pricing!$B$16-Pricing!$B$17)*Pricing!$B$17 | J4: =MAX(0,1-((F4*Pricing!$B$3*(1-Pricing!$B$15-Pricing!$B$16-Pricing!$B$17)/(1+Pricing!$B$18))-(Pricing!$B$6+Pricing!$B$7+Pricing!$B$8+Pricing!$B$9+Pricing!$B$10+Pricing!$B$11+Pricing!$B$12+Pricing!$B$13))/(F4*Pricing!$B$3)) | K4: Fiorese Jewelry | L4: 7
A5: 2 | B5: Round Lab Diamond Heart Pendant Charm Bracelet | C5: Stone Spec: Round Cut Lab Diamond DEF VS Please note, kindly specify your bracelet size in the remarks when placing the order. If you have any special requests for this design (such as metal, gemstone, or design details), please contact our advisor for customization. Description Sweet and refined, this charm bracelet features a delicate chain accented with a heart-shaped pendant adorned with round lab diamonds , symbolizing love with a soft, radiant sparkle. The round diamonds add timeless… | D5: 2mm (per stone) | E5: 18K Gold | F5: 1204 | G5: =F5*(1-Pricing!$B$4)*Pricing!$B$3+(Pricing!$B$6+Pricing!$B$7+Pricing!$B$8+Pricing!$B$9+Pricing!$B$10+Pricing!$B$11+Pricing!$B$12+Pricing!$B$13) | H5: =G5/(1-Pricing!$B$15-Pricing!$B$16-Pricing!$B$17)*(1+Pricing!$B$18) | I5: =G5/(1-Pricing!$B$15-Pricing!$B$16-Pricing!$B$17)*Pricing!$B$17 | J5: =MAX(0,1-((F5*Pricing!$B$3*(1-Pricing!$B$15-Pricing!$B$16-Pricing!$B$17)/(1+Pricing!$B$18))-(Pricing!$B$6+Pricing!$B$7+Pricing!$B$8+Pricing!$B$9+Pricing!$B$10+Pricing!$B$11+Pricing!$B$12+Pricing!$B$13))/(F5*Pricing!$B$3)) | K5: Fiorese Jewelry | L5: 4
A6: 3 | B6: 3.5mm Round Lab Diamond 3-Stone Bezel-Set Adjustable Station Bracelet | C6: Stone Spec: 3.5mm Round Cut Lab Diamond, DEF VS, about 0.45 ct tw Please note, kindly specify your bracelet size in the remarks when placing the order. If you have any special requests for this design (such as metal, gemstone, or design details), please contact our advisor for customization. Description Delicate and effortlessly refined, this adjustable station bracelet features three 3.5mm round lab diamonds , thoughtfully spaced along a fine chain to create a balanced and airy silhouette.… | D6: 0.45 ct | E6: 18K Gold | F6: 1300.8 | G6: =F6*(1-Pricing!$B$4)*Pricing!$B$3+(Pricing!$B$6+Pricing!$B$7+Pricing!$B$8+Pricing!$B$9+Pricing!$B$10+Pricing!$B$11+Pricing!$B$12+Pricing!$B$13) | H6: =G6/(1-Pricing!$B$15-Pricing!$B$16-Pricing!$B$17)*(1+Pricing!$B$18) | I6: =G6/(1-Pricing!$B$15-Pricing!$B$16-Pricing!$B$17)*Pricing!$B$17 | J6: =MAX(0,1-((F6*Pricing!$B$3*(1-Pricing!$B$15-Pricing!$B$16-Pricing!$B$17)/(1+Pricing!$B$18))-(Pricing!$B$6+Pricing!$B$7+Pricing!$B$8+Pricing!$B$9+Pricing!$B$10+Pricing!$B$11+Pricing!$B$12+Pricing!$B$13))/(F6*Pricing!$B$3)) | K6: Fiorese Jewelry | L6: 4
A7: 4 | B7: Round Lab Diamond Toi et Moi Pendant Chain Bracelet | C7: Stone Spec: 1.2mm Radiant Cut Lab Diamond DEF VS, about 0.17 ct tw Pendant Size: 25*6.6mm Please note, kindly specify your bracelet size in the remarks when placing the order. If you have any special requests for this design (such as metal, gemstone, or design details), please contact our advisor for customization. Description Refined and meaningful, this chain bracelet features a distinctive Toi-et-Moi pendant , pairing a round lab diamond centerpiece with a rectangular ring motif set with… | D7: 0.17 ct | E7: 18K Gold | F7: 1423.2 | G7: =F7*(1-Pricing!$B$4)*Pricing!$B$3+(Pricing!$B$6+Pricing!$B$7+Pricing!$B$8+Pricing!$B$9+Pricing!$B$10+Pricing!$B$11+Pricing!$B$12+Pricing!$B$13) | H7: =G7/(1-Pricing!$B$15-Pricing!$B$16-Pricing!$B$17)*(1+Pricing!$B$18) | I7: =G7/(1-Pricing!$B$15-Pricing!$B$16-Pricing!$B$17)*Pricing!$B$17 | J7: =MAX(0,1-((F7*Pricing!$B$3*(1-Pricing!$B$15-Pricing!$B$16-Pricing!$B$17)/(1+Pricing!$B$18))-(Pricing!$B$6+Pricing!$B$7+Pricing!$B$8+Pricing!$B$9+Pricing!$B$10+Pricing!$B$11+Pricing!$B$12+Pricing!$B$13))/(F7*Pricing!$B$3)) | K7: Fiorese Jewelry | L7: 5
A8: 5 | B8: 3mm Round Lab Diamond Bezel-Set Station Bracelet | C8: Stone Spec: 3mm Round Cut Lab Diamond, DEF VS, about 0.77 ct tw Please note, kindly specify your bracelet size in the remarks when placing the order. If you have any special requests for this design (such as metal, gemstone, or design details), please contact our advisor for customization. Description Clean and effortlessly refined, this station bracelet features 3mm round lab diamonds delicately spaced along a fine chain, creating a light, balanced silhouette with subtle, continuous sparkle.… | D8: 0.77 ct | E8: 18K Gold | F8: 1423.2 | G8: =F8*(1-Pricing!$B$4)*Pricing!$B$3+(Pricing!$B$6+Pricing!$B$7+Pricing!$B$8+Pricing!$B$9+Pricing!$B$10+Pricing!$B$11+Pricing!$B$12+Pricing!$B$13) | H8: =G8/(1-Pricing!$B$15-Pricing!$B$16-Pricing!$B$17)*(1+Pricing!$B$18) | I8: =G8/(1-Pricing!$B$15-Pricing!$B$16-Pricing!$B$17)*Pricing!$B$17 | J8: =MAX(0,1-((F8*Pricing!$B$3*(1-Pricing!$B$15-Pricing!$B$16-Pricing!$B$17)/(1+Pricing!$B$18))-(Pricing!$B$6+Pricing!$B$7+Pricing!$B$8+Pricing!$B$9+Pricing!$B$10+Pricing!$B$11+Pricing!$B$12+Pricing!$B$13))/(F8*Pricing!$B$3)) | K8: Fiorese Jewelry | L8: 3
A9: 6 | B9: 3mm Round Lab Diamond 5-Stone Bezel-Set Adjustable Station Bracelet | C9: Stone Spec: 3mm Round Cut Lab Diamond, DEF VS, about 0.5 ct tw Please note, kindly specify your bracelet size in the remarks when placing the order. If you have any special requests for this design (such as metal, gemstone, or design details), please contact our advisor for customization. Description Light, refined, and effortlessly wearable, this adjustable station bracelet features five 3mm round lab diamonds , evenly spaced along a fine chain to create a graceful, balanced silhouette. The… | D9: 0.5 ct | E9: 18K Gold | F9: 1473.6 | G9: =F9*(1-Pricing!$B$4)*Pricing!$B$3+(Pricing!$B$6+Pricing!$B$7+Pricing!$B$8+Pricing!$B$9+Pricing!$B$10+Pricing!$B$11+Pricing!$B$12+Pricing!$B$13) | H9: =G9/(1-Pricing!$B$15-Pricing!$B$16-Pricing!$B$17)*(1+Pricing!$B$18) | I9: =G9/(1-Pricing!$B$15-Pricing!$B$16-Pricing!$B$17)*Pricing!$B$17 | J9: =MAX(0,1-((F9*Pricing!$B$3*(1-Pricing!$B$15-Pricing!$B$16-Pricing!$B$17)/(1+Pricing!$B$18))-(Pricing!$B$6+Pricing!$B$7+Pricing!$B$8+Pricing!$B$9+Pricing!$B$10+Pricing!$B$11+Pricing!$B$12+Pricing!$B$13))/(F9*Pricing!$B$3)) | K9: Fiorese Jewelry | L9: 4
A10: 7 | B10: Round Lab Diamond Leaf-Cluster Chain Bracelet | C10: Stone Spec: Round Cut Lab Diamond DEF VS, about 0.3 ct tw Cluster Length: 32mm Please note, kindly specify your bracelet size in the remarks when placing the order. If you have any special requests for this design (such as metal, gemstone, or design details), please contact our advisor for customization. Description Graceful and organically inspired, this chain bracelet features clusters of round lab diamonds arranged in a delicate leaf motif , creating a soft, flowing pattern along the wrist.… | D10: 0.3 ct | E10: 18K Gold | F10: 1703.2 | G10: =F10*(1-Pricing!$B$4)*Pricing!$B$3+(Pricing!$B$6+Pricing!$B$7+Pricing!$B$8+Pricing!$B$9+Pricing!$B$10+Pricing!$B$11+Pricing!$B$12+Pricing!$B$13) | H10: =G10/(1-Pricing!$B$15-Pricing!$B$16-Pricing!$B$17)*(1+Pricing!$B$18) | I10: =G10/(1-Pricing!$B$15-Pricing!$B$16-Pricing!$B$17)*Pricing!$B$17 | J10: =MAX(0,1-((F10*Pricing!$B$3*(1-Pricing!$B$15-Pricing!$B$16-Pricing!$B$17)/(1+Pricing!$B$18))-(Pricing!$B$6+Pricing!$B$7+Pricing!$B$8+Pricing!$B$9+Pricing!$B$10+Pricing!$B$11+Pricing!$B$12+Pricing!$B$13))/(F10*Pricing!$B$3)) | K10: Fiorese Jewelry | L10: 4
A11: 8 | B11: Round Lab Diamond Viper-Inspired Bangle Bracelet | C11: Stone Spec: Round Cut Lab Diamond DEF VS about 3.66 ct tw Please note, kindly specify your bracelet size in the remarks when placing the order. If you have any special requests for this design (such as metal, gemstone, or design details), please contact our advisor for customization. Description Bold, sculptural, and undeniably captivating, this viper-inspired bangle bracelet features shimmering round lab diamonds arranged within a sleek serpentine silhouette that wraps gracefully around the… | D11: 3.66 ct | E11: 925 Sterling Silver | F11: 1809.6 | G11: =F11*(1-Pricing!$B$4)*Pricing!$B$3+(Pricing!$B$6+Pricing!$B$7+Pricing!$B$8+Pricing!$B$9+Pricing!$B$10+Pricing!$B$11+Pricing!$B$12+Pricing!$B$13) | H11: =G11/(1-Pricing!$B$15-Pricing!$B$16-Pricing!$B$17)*(1+Pricing!$B$18) | I11: =G11/(1-Pricing!$B$15-Pricing!$B$16-Pricing!$B$17)*Pricing!$B$17 | J11: =MAX(0,1-((F11*Pricing!$B$3*(1-Pricing!$B$15-Pricing!$B$16-Pricing!$B$17)/(1+Pricing!$B$18))-(Pricing!$B$6+Pricing!$B$7+Pricing!$B$8+Pricing!$B$9+Pricing!$B$10+Pricing!$B$11+Pricing!$B$12+Pricing!$B$13))/(F11*Pricing!$B$3)) | K11: Fiorese Jewelry | L11: 5
A12: 9 | B12: Round Lab Diamond Star Bezel-Set Station Bracelet | C12: Stone Spec: Round Cut Lab Diamond DEF VS Stone Size Guide (Based on 6" Bracelet) Total Carat Weight ~1.62 ct tw Please note, kindly specify your bracelet size in the remarks when placing the order. If you have any special requests for this design (such as metal, gemstone, or design details), please contact our advisor for customization. Description Whimsical and refined, this station bracelet features round lab diamonds framed in distinctive star-shaped bezel settings , creating a… | D12: 1.62 ct | E12: 18K Gold | F12: 2132.8 | G12: =F12*(1-Pricing!$B$4)*Pricing!$B$3+(Pricing!$B$6+Pricing!$B$7+Pricing!$B$8+Pricing!$B$9+Pricing!$B$10+Pricing!$B$11+Pricing!$B$12+Pricing!$B$13) | H12: =G12/(1-Pricing!$B$15-Pricing!$B$16-Pricing!$B$17)*(1+Pricing!$B$18) | I12: =G12/(1-Pricing!$B$15-Pricing!$B$16-Pricing!$B$17)*Pricing!$B$17 | J12: =MAX(0,1-((F12*Pricing!$B$3*(1-Pricing!$B$15-Pricing!$B$16-Pricing!$B$17)/(1+Pricing!$B$18))-(Pricing!$B$6+Pricing!$B$7+Pricing!$B$8+Pricing!$B$9+Pricing!$B$10+Pricing!$B$11+Pricing!$B$12+Pricing!$B$13))/(F12*Pricing!$B$3)) | K12: Fiorese Jewelry | L12: 3
A13: 10 | B13: Round Lab Diamond Ring-Shaped Pave Pendant Chain Bracelet | C13: Stone Spec: 1.5mm Round Cut Lab Diamond DEF VS, about 0.57 ct tw Pendant Size: 23mm Please note, kindly specify your bracelet size in the remarks when placing the order. If you have any special requests for this design (such as metal, gemstone, or design details), please contact our advisor for customization. Description Modern and symbolic, this chain bracelet features a refined ring-shaped pendant set with round lab diamonds , creating a continuous circle of light that represents unity and… | D13: 0.57 ct | E13: 18K Gold | F13: 2873.6 | G13: =F13*(1-Pricing!$B$4)*Pricing!$B$3+(Pricing!$B$6+Pricing!$B$7+Pricing!$B$8+Pricing!$B$9+Pricing!$B$10+Pricing!$B$11+Pricing!$B$12+Pricing!$B$13) | H13: =G13/(1-Pricing!$B$15-Pricing!$B$16-Pricing!$B$17)*(1+Pricing!$B$18) | I13: =G13/(1-Pricing!$B$15-Pricing!$B$16-Pricing!$B$17)*Pricing!$B$17 | J13: =MAX(0,1-((F13*Pricing!$B$3*(1-Pricing!$B$15-Pricing!$B$16-Pricing!$B$17)/(1+Pricing!$B$18))-(Pricing!$B$6+Pricing!$B$7+Pricing!$B$8+Pricing!$B$9+Pricing!$B$10+Pricing!$B$11+Pricing!$B$12+Pricing!$B$13))/(F13*Pricing!$B$3)) | K13: Fiorese Jewelry | L13: 6
A14: 11 | B14: Round Lab Diamond Fancy-Shape Station Chain Bracelet | C14: Stone Spec: Round Cut Lab Diamond, DEF VS, about 2 ct tw Please note, kindly specify your bracelet size in the remarks when placing the order. If you have any special requests for this design (such as metal, gemstone, or design details), please contact our advisor for customization. Description Playful yet refined, this station chain bracelet features a harmonious mix of round lab diamonds and fancy-shaped accents , creating a dynamic interplay of light and form along a delicate chain. The… | D14: 2 ct | E14: 18K Gold | F14: 2926.4 | G14: =F14*(1-Pricing!$B$4)*Pricing!$B$3+(Pricing!$B$6+Pricing!$B$7+Pricing!$B$8+Pricing!$B$9+Pricing!$B$10+Pricing!$B$11+Pricing!$B$12+Pricing!$B$13) | H14: =G14/(1-Pricing!$B$15-Pricing!$B$16-Pricing!$B$17)*(1+Pricing!$B$18) | I14: =G14/(1-Pricing!$B$15-Pricing!$B$16-Pricing!$B$17)*Pricing!$B$17 | J14: =MAX(0,1-((F14*Pricing!$B$3*(1-Pricing!$B$15-Pricing!$B$16-Pricing!$B$17)/(1+Pricing!$B$18))-(Pricing!$B$6+Pricing!$B$7+Pricing!$B$8+Pricing!$B$9+Pricing!$B$10+Pricing!$B$11+Pricing!$B$12+Pricing!$B$13))/(F14*Pricing!$B$3)) | K14: Fiorese Jewelry | L14: 6
A15: 12 | B15: Round Lab Diamond Pave Force Rope Chain Bracelet | C15: Stone Spec: Round Cut Lab Diamond DEF VS, 0.78 ct tw Please note, kindly specify your bracelet size in the remarks when placing the order. If you have any special requests for this design (such as metal, gemstone, or design details), please contact our advisor for customization. Description Bold and contemporary, this force rope chain bracelet features shimmering round lab diamonds in a refined pavé setting , combining the strength of classic chain styling with elevated fine jewelry… | D15: 0.78 ct | E15: 18K Gold | F15: 3378.4 | G15: =F15*(1-Pricing!$B$4)*Pricing!$B$3+(Pricing!$B$6+Pricing!$B$7+Pricing!$B$8+Pricing!$B$9+Pricing!$B$10+Pricing!$B$11+Pricing!$B$12+Pricing!$B$13) | H15: =G15/(1-Pricing!$B$15-Pricing!$B$16-Pricing!$B$17)*(1+Pricing!$B$18) | I15: =G15/(1-Pricing!$B$15-Pricing!$B$16-Pricing!$B$17)*Pricing!$B$17 | J15: =MAX(0,1-((F15*Pricing!$B$3*(1-Pricing!$B$15-Pricing!$B$16-Pricing!$B$17)/(1+Pricing!$B$18))-(Pricing!$B$6+Pricing!$B$7+Pricing!$B$8+Pricing!$B$9+Pricing!$B$10+Pricing!$B$11+Pricing!$B$12+Pricing!$B$13))/(F15*Pricing!$B$3)) | K15: Fiorese Jewelry | L15: 7
... A658: 655 | B658: Princess-Cut Lab Diamond 7-Stone Half Eternity Ring with Tapered Band | C658: Stone Spec: 7 pieces of 4*4mm princess cut lab diamond DEF VS about 3.2 ct tw Band Width: 2.8mm Band Thickness: 1.7mm If you have any special requests for this design (such as metal, gemstone, or design details), please contact our advisor for customization. Description Elegant, modern, and beautifully balanced, this 7-stone half eternity ring features a row of radiant princess-cut lab diamonds arranged in a refined composition that showcases crisp geometry and exceptional brilliance. The… | D658: 3.2 ct | E658: 18K Gold | F658: 3413.25 | G658: =F658*(1-Pricing!$B$4)*Pricing!$B$3+(Pricing!$B$6+Pricing!$B$7+Pricing!$B$8+Pricing!$B$9+Pricing!$B$10+Pricing!$B$11+Pricing!$B$12+Pricing!$B$13) | H658: =G658/(1-Pricing!$B$15-Pricing!$B$16-Pricing!$B$17)*(1+Pricing!$B$18) | I658: =G658/(1-Pricing!$B$15-Pricing!$B$16-Pricing!$B$17)*Pricing!$B$17 | J658: =MAX(0,1-((F658*Pricing!$B$3*(1-Pricing!$B$15-Pricing!$B$16-Pricing!$B$17)/(1+Pricing!$B$18))-(Pricing!$B$6+Pricing!$B$7+Pricing!$B$8+Pricing!$B$9+Pricing!$B$10+Pricing!$B$11+Pricing!$B$12+Pricing!$B$13))/(F658*Pricing!$B$3)) | K658: Fiorese Jewelry | L658: 6

Sheet Pricing
A1: PRICING MODEL — from your LOMOND cost sheet · edit the yellow cells only
A2: PURCHASE
A3: USD → SAR exchange rate | B3: 3.75 | C3: From your settings sheet.
A4: Wholesale discount off the listed price | B4: 0.4 | C4: ★ ASSUMPTION — replace with the rate you actually negotiate. The listed prices are the suppliers’ RETAIL prices; your three purchases (P-001/2/3) match catalogue items almost exactly, so you are currently paying full retail. Column U shows the discount each piece needs.
A5: COST PER PIECE (SAR) — taken from your cost statement
A6: Bank transfer fee | B6: 47.5 | C6: $38 per shipment ÷ 3 pieces × 3.75.
A7: Import shipping | B7: 131.25 | C7: $35 per shipment × 3.75 ÷ pieces per shipment.
A8: Customs / duty | B8: 21 | C8: Per imported piece.
A9: Delivery to the customer | B9: 30
A10: Share of one-off set-up costs | B10: 211.43 | C10: 10,571.44 ÷ 50 pieces.
A11: Packaging, cards, box per piece | B11: 51.08
A12: Share of monthly running costs | B12: 53.18 | C12: 2,659 ÷ 50 pieces.
A13: Logo engraving | B13: 3.4 | C13: 170 ÷ 50 pieces.
A14: FEES, MARGIN AND TAX
A15: Processing fees | B15: 0.08 | C15: From your settings sheet.
A16: Payment gateway fees | B16: 0.038 | C16: From your settings sheet.
A17: NET PROFIT MARGIN | B17: 0.08 | C17: ★ Your net profit as a share of the pre-VAT price — the same basis your own sheet uses. Set to 8%, above the 5% floor you asked for.
A18: VAT | B18: 0.15 | C18: Collected on behalf of ZATCA — not profit.
A20: HOW EACH PRICE IS BUILT
A21: Your Buy Price (USD) | C21: Listed Price × (1 − wholesale discount)
A22: Purchase (SAR) | C22: Buy Price × exchange rate
A23: Overhead (SAR) | C23: sum of the eight cost rows above
A24: TOTAL COST (SAR) | C24: Purchase + Overhead
A25: Price before VAT | C25: Total Cost ÷ (1 − processing − gateway − margin)
A26: FINAL PRICE (SAR) | C26: Price before VAT × 1.15
A27: Net Profit (SAR) | C27: Price before VAT × margin
A28: Discount needed (col U) | C28: the wholesale discount at which your price equals the supplier’s own retail price
A30: ⚠ WHY THE PRICES LOOKED TOO HIGH Your overhead is about 549 SAR on every single piece, and fees + margin + VAT multiply the cost by roughly 1.43. So at full retail your price lands about 1.5× the supplier’s own website price — no customer would pay that. Cutting the margin does not fix it: even at 0% profit the median piece still comes out around 7,976 SAR, because the base price is already retail. The lever is the wholesale discount (B4). At an 8% margin the median piece needs about 37% off, and cheaper pieces need far more because the 549 SAR overhead is fixed: a 2,000 SAR piece needs ~58%, a 1,000 SAR piece ~85%. Two practical consequences: negotiate OEM/wholesale rates with the suppliers (all three run B2B programmes and Provence Gems is itself the factory), and concentrate on higher-value pieces until volume brings the fixed share per piece down.

Sheet Summary
A1: FULL PHOTO GALLERY — Part 1 — Fiorese Jewelry
A3: All pricing controls live on the Pricing sheet.
A7: CONTENTS
A8: Items in this file | B8: 655
A9: Photos embedded | B9: 3733
A10: Photos per item | B10: average 5.7 · maximum 14
A11: Price range (USD) | B11: $614.25 – $109,251.00
A12: Final price | B12: Built on the Pricing sheet: listed price → wholesale discount → landed cost → profit %
A13: Links | B13: Omitted by request — product and image links are in the main workbook.
A15: SOURCES
A16: Fiorese Jewelry | B16: 655 items
A18: BY METAL
A19: 18K Gold | B19: 632 items
A20: 18K White Gold | B20: 10 items
A21: 925 Sterling Silver | B21: 9 items
A22: 18K Yellow Gold | B22: 4 items
A24: BY CATEGORY
A25: Engagement Ring | B25: 225 items
A26: Necklace | B26: 113 items
A27: Tennis Bracelet | B27: 105 items
A28: Tennis Necklace | B28: 88 items
A29: Stud Earrings | B29: 60 items
A30: Bracelet | B30: 24 items
A31: Hoop Earrings | B31: 19 items
A32: Wedding/Eternity Band | B32: 15 items
A33: Earrings | B33: 3 items
A34: Ring | B34: 2 items
A35: Jewelry | B35: 1 items
